Workbook
Name Currency_name: [1]Input!$D$24

Sheet Title
C15: Финансово-экономическая модель
B16: =IF(C16="","Название проекта:","") | C16: Строительство производства сухих строительных смесей
D18: Ввводные данные
C19: Link 1 | D19: Ссылка
C20: Calculate | D20: Расчет
C21: Other | D21: Изменение формулы
D22: Техническая ячейка
C26: Автор: Баринова К.О.

Sheet Input
A1: =Title!$C$16 -> Строительство производства сухих строительных смесей
A2: =Title!$C$15 -> Финансово-экономическая модель | L2: =DATE(($H$9),1,1) -> 45292 | M2: =IFERROR(IF(YEAR(L3)<YEAR(EDATE($H$12,$H$13*12)-1),L3+1,""),"") -> 45658 | N2: =IFERROR(IF(YEAR(M3)<YEAR(EDATE($H$12,$H$13*12)-1),M3+1,""),"") -> 46023 | O2: =IFERROR(IF(YEAR(N3)<YEAR(EDATE($H$12,$H$13*12)-1),N3+1,""),"") -> 46388 | P2: =IFERROR(IF(YEAR(O3)<YEAR(EDATE($H$12,$H$13*12)-1),O3+1,""),"") -> 46753 | Q2: =IFERROR(IF(YEAR(P3)<YEAR(EDATE($H$12,$H$13*12)-1),P3+1,""),"") -> 47119 | R2: =IFERROR(IF(YEAR(Q3)<YEAR(EDATE($H$12,$H$13*12)-1),Q3+1,""),"") -> 47484 | S2: =IFERROR(IF(YEAR(R3)<YEAR(EDATE($H$12,$H$13*12)-1),R3+1,""),"") -> 47849 | T2: =IFERROR(IF(YEAR(S3)<YEAR(EDATE($H$12,$H$13*12)-1),S3+1,""),"") -> 48214 | ... AN2: =IFERROR(IF(YEAR(AM3)<YEAR(EDATE($H$12,$H$13*12)-1),AM3+1,""),"")
A3: Входные данные | L3: =DATE(YEAR(L2),12,31) -> 45657 | M3: =IFERROR(DATE(YEAR(M2),12,31),"") -> 46022 | N3: =IFERROR(DATE(YEAR(N2),12,31),"") -> 46387 | O3: =IFERROR(DATE(YEAR(O2),12,31),"") -> 46752 | P3: =IFERROR(DATE(YEAR(P2),12,31),"") -> 47118 | Q3: =IFERROR(DATE(YEAR(Q2),12,31),"") -> 47483 | R3: =IFERROR(DATE(YEAR(R2),12,31),"") -> 47848 | S3: =IFERROR(DATE(YEAR(S2),12,31),"") -> 48213 | T3: =IFERROR(DATE(YEAR(T2),12,31),"") -> 48579 | ... AN3: =IFERROR(DATE(YEAR(AN2),12,31),"")
L4: =IFERROR(IF(YEAR(L3)<YEAR($H$10),"Факт","Прогноз"),"") -> Факт | M4: =IFERROR(IF(YEAR(M3)<YEAR($H$10),"Факт","Прогноз"),"") -> Прогноз | N4: =IFERROR(IF(YEAR(N3)<YEAR($H$10),"Факт","Прогноз"),"") -> Прогноз | O4: =IFERROR(IF(YEAR(O3)<YEAR($H$10),"Факт","Прогноз"),"") -> Прогноз | P4: =IFERROR(IF(YEAR(P3)<YEAR($H$10),"Факт","Прогноз"),"") -> Прогноз | Q4: =IFERROR(IF(YEAR(Q3)<YEAR($H$10),"Факт","Прогноз"),"") -> Прогноз | R4: =IFERROR(IF(YEAR(R3)<YEAR($H$10),"Факт","Прогноз"),"") -> Прогноз | S4: =IFERROR(IF(YEAR(S3)<YEAR($H$10),"Факт","Прогноз"),"") -> Прогноз | ... AN4: =IFERROR(IF(YEAR(AN3)<YEAR($H$10),"Факт","Прогноз"),"")
G5: Ед. измерения | H5: Значение/База | J5: Сумма
B7: ВВОДНЫЕ ВРЕМЕННЫЕ ПАРАМЕТРЫ МОДЕЛИ
B9: Дата начала анализа | G9: дата | H9: 2024
B10: Дата начала прогнозного периода | G10: дата | H10: 45658
B11: Дата начала инвестиционной деятельности | G11: дата | H11: 45658
B12: Дата начала операционной деятельности | G12: дата | H12: 46082
B13: Горизонт планирования | G13: лет | H13: 15 | I13: // не более 29 лет с даты начала анализа
B14: Дата окончания операционной деятельности | G14: дата | H14: =EDATE(H12,H13*12) -> 51561
B15: Базовый год индексации | G15: год | H15: 2024
B16: Дата начала оптимизации состава продукции | G16: дата | H16: 49126
B17: Возмещать НДС из бюджета | G17: х | I17: TRUE
B19: МАКРОЭКОНОМИЧЕСКИЕ ПАРАМЕТРЫ ПРОЕКТА
B21: Обменный курс рубля к доллару | G21: RUB/USD | L21: 59 | M21: 60 | N21: 61 | O21: 62 | P21: 63 | Q21: 59 | R21: 59 | S21: 59 | T21: 59 | U21: 59 | V21: 59 | W21: 59 | X21: 59 | Y21: 59 | Z21: 59 | AA21: 59 | AB21: 59 | AC21: 59
B22: CPI, (RUB) | G22: х | L22: 1.04 | M22: 1.04 | N22: 1.04 | O22: 1.04 | P22: 1.04 | Q22: 1.04 | R22: 1.04 | S22: 1.04 | T22: 1.04 | U22: 1.04 | V22: 1.04 | W22: 1.04 | X22: 1.04 | Y22: 1.04 | Z22: 1.04 | AA22: 1.04 | AB22: 1.04 | AC22: 1.04
B23: PPI, (RUB) | G23: х | L23: 1.04 | M23: 1.04 | N23: 1.04 | O23: 1.04 | P23: 1.04 | Q23: 1.04 | R23: 1.04 | S23: 1.04 | T23: 1.04 | U23: 1.04 | V23: 1.04 | W23: 1.04 | X23: 1.04 | Y23: 1.04 | Z23: 1.04 | AA23: 1.04 | AB23: 1.04 | AC23: 1.04
B24: PPI, (USD) | G24: х | L24: 1.03 | M24: 1.03 | N24: 1.03 | O24: 1.03 | P24: 1.03 | Q24: 1.03 | R24: 1.03 | S24: 1.03 | T24: 1.03 | U24: 1.03 | V24: 1.03 | W24: 1.03 | X24: 1.03 | Y24: 1.03 | Z24: 1.03 | AA24: 1.03 | AB24: 1.03 | AC24: 1.03
B25: Индекс роста заработной платы (RUB) | G25: х | L25: 1.04 | M25: 1.04 | N25: 1.04 | O25: 1.04 | P25: 1.04 | Q25: 1.04 | R25: 1.04 | S25: 1.04 | T25: 1.04 | U25: 1.04 | V25: 1.04 | W25: 1.04 | X25: 1.04 | Y25: 1.04 | Z25: 1.04 | AA25: 1.04 | AB25: 1.04 | AC25: 1.04
B26: Индекс роста цен на естественные монополии (электроэнергия) | G26: х | L26: 1.05 | M26: 1.05 | N26: 1.05 | O26: 1.05 | P26: 1.05 | Q26: 1.05 | R26: 1.05 | S26: 1.05 | T26: 1.05 | U26: 1.05 | V26: 1.05 | W26: 1.05 | X26: 1.05 | Y26: 1.05 | Z26: 1.05 | AA26: 1.05 | AB26: 1.05 | AC26: 1.05
B27: Ключевая ставка ЦБ РФ | G27: % | L27: 0.21 | M27: 0.2 | N27: 0.15 | O27: 0.11 | P27: 0.1 | Q27: 0.08 | R27: 0.07 | S27: 0.07 | T27: 0.07 | U27: 0.07 | V27: 0.07 | W27: 0.07 | X27: 0.07 | Y27: 0.07 | Z27: 0.07 | AA27: 0.07 | AB27: 0.07 | AC27: 0.07
B29: НАЛОГОВОЕ ОКРУЖЕНИЕ ПРОЕКТА
B31: Доля прибыли к зачету против убытков | G31: % | L31: 0.5 | M31: 0.5 | N31: 0.5 | O31: 0.5 | P31: 0.5 | Q31: 0.5 | R31: 0.5 | S31: 0.5 | T31: 0.5 | U31: 0.5 | V31: 0.5 | W31: 0.5 | X31: 0.5 | Y31: 0.5 | Z31: 0.5 | AA31: 0.5 | AB31: 0.5 | AC31: 0.5
B32: НДС | G32: % | L32: 0.2 | M32: 0.2 | N32: 0.2 | O32: 0.2 | P32: 0.2 | Q32: 0.2 | R32: 0.2 | S32: 0.2 | T32: 0.2 | U32: 0.2 | V32: 0.2 | W32: 0.2 | X32: 0.2 | Y32: 0.2 | Z32: 0.2 | AA32: 0.2 | AB32: 0.2 | AC32: 0.2
B33: Ставка налога на прибыль | G33: % | L33: 0.2 | M33: 0.25 | N33: 0.25 | O33: 0.25 | P33: 0.25 | Q33: 0.25 | R33: 0.25 | S33: 0.25 | T33: 0.25 | U33: 0.25 | V33: 0.25 | W33: 0.25 | X33: 0.25 | Y33: 0.25 | Z33: 0.25 | AA33: 0.25 | AB33: 0.25 | AC33: 0.25
B34: Ставка налога на имущество | G34: % | L34: 0.022 | M34: 0.022 | N34: 0.022 | O34: 0.022 | P34: 0.022 | Q34: 0.022 | R34: 0.022 | S34: 0.022 | T34: 0.022 | U34: 0.022 | V34: 0.022 | W34: 0.022 | X34: 0.022 | Y34: 0.022 | Z34: 0.022 | AA34: 0.022 | AB34: 0.022 | AC34: 0.022
B35: Ставка налога на землю | G35: % | L35: 0.015 | M35: 0.015 | N35: 0.015 | O35: 0.015 | P35: 0.015 | Q35: 0.015 | R35: 0.015 | S35: 0.015 | T35: 0.015 | U35: 0.015 | V35: 0.015 | W35: 0.015 | X35: 0.015 | Y35: 0.015 | Z35: 0.015 | AA35: 0.015 | AB35: 0.015 | AC35: 0.015
B36: Ставка транспортного налога | G36: руб./л.с. | L36: 2.5 | M36: 2.5 | N36: 2.5 | O36: 2.5 | P36: 2.5 | Q36: 2.5 | R36: 2.5 | S36: 2.5 | T36: 2.5 | U36: 2.5 | V36: 2.5 | W36: 2.5 | X36: 2.5 | Y36: 2.5 | Z36: 2.5 | AA36: 2.5 | AB36: 2.5 | AC36: 2.5
B37: Социальные отчисления (ПФР, ФСС, ФОМС) | G37: % | L37: 0.302 | M37: 0.302 | N37: 0.302 | O37: 0.302 | P37: 0.302 | Q37: 0.302 | R37: 0.302 | S37: 0.302 | T37: 0.302 | U37: 0.302 | V37: 0.302 | W37: 0.302 | X37: 0.302 | Y37: 0.302 | Z37: 0.302 | AA37: 0.302 | AB37: 0.302 | AC37: 0.302
B38: Социальные отчисления от несчастных случаев и проф. заболеваний (рабочие) | G38: % | L38: 0.08 | M38: 0.08 | N38: 0.08 | O38: 0.08 | P38: 0.08 | Q38: 0.08 | R38: 0.08 | S38: 0.08 | T38: 0.08 | U38: 0.08 | V38: 0.08 | W38: 0.08 | X38: 0.08 | Y38: 0.08 | Z38: 0.08 | AA38: 0.08 | AB38: 0.08 | AC38: 0.08
B39: Социальные отчисления от несчастных случаев и проф. заболеваний (служащие) | G39: % | L39: 0.05 | M39: 0.05 | N39: 0.05 | O39: 0.05 | P39: 0.05 | Q39: 0.05 | R39: 0.05 | S39: 0.05 | T39: 0.05 | U39: 0.05 | V39: 0.05 | W39: 0.05 | X39: 0.05 | Y39: 0.05 | Z39: 0.05 | AA39: 0.05 | AB39: 0.05 | AC39: 0.05
B41: КАПИТАЛЬНЫЕ И ПОДДЕРЖИВАЮЩИЕ ВЛОЖЕНИЯ
B43: Общие капитальные вложения проекта, без НДС | G43: млн руб. | H43: 215
B45: Доля импорта (оборудование) | G45: % | H45: 0.3
B47: Доля импорта (транспорт) | G47: % | H47: 0.3
B49: Доля недвижимого имущества (от общей стоимости зданий, сооружений, оборудования) | G49: % | H49: 0.5
B51: Капитальные вложения разбивка по направлениям
C52: Земля | G52: % | H52: 0
C53: Здания и сооружения | G53: % | H53: 0.2
C54: Оборудование | G54: % | H54: 0.7
C55: Транспорт | G55: % | H55: 0.1
B57: Капитальные вложения освоение по годам | K57: =YEAR(H11) -> 2025 | L57: =IF(K57<YEAR($H$12),K57+1,"") -> 2026 | M57: =IF(L57<YEAR($H$12),L57+1,"") | N57: =IF(M57<YEAR($H$12),M57+1,"") | O57: =IF(N57<YEAR($H$12),N57+1,"") | P57: =IF(O57<YEAR($H$12),O57+1,"") | Q57: =IF(P57<YEAR($H$12),P57+1,"")
C58: Земля | G58: % | H58: =SUM(K58:Q58) -> 0 | K58: 0 | L58: 0
C59: Здания и сооружения | G59: % | H59: =SUM(K59:Q59) -> 1 | K59: 0.5 | L59: 0.5
C60: Оборудование | G60: % | H60: =SUM(K60:Q60) -> 1 | K60: 0.75 | L60: 0.25
C61: Транспорт | G61: % | H61: =SUM(K61:Q61) -> 1 | K61: 0.25 | L61: 0.75
B63: Капитальные вложения финансирование по годам | K63: =YEAR(H11) -> 2025 | L63: =IF(K63<YEAR($H$12),K63+1,"") -> 2026 | M63: =IF(L63<YEAR($H$12),L63+1,"") | N63: =IF(M63<YEAR($H$12),M63+1,"") | O63: =IF(N63<YEAR($H$12),N63+1,"") | P63: =IF(O63<YEAR($H$12),O63+1,"") | Q63: =IF(P63<YEAR($H$12),P63+1,"")
A64: CPI, (RUB) | C64: Земля | G64: % | H64: =SUM(K64:Q64) -> 0 | K64: 0 | L64: 0
A65: PPI, (RUB) | C65: Здания и сооружения | G65: % | H65: =SUM(K65:Q65) -> 1 | K65: 0.5 | L65: 0.5
A66: PPI, (RUB) | C66: Оборудование | G66: % | H66: =SUM(K66:Q66) -> 1 | K66: 0.5 | L66: 0.5
A67: PPI, (RUB) | C67: Транспорт | G67: % | H67: =SUM(K67:Q67) -> 1 | K67: 0.5 | L67: 0.5
B69: Срок амортизации
C70: Здания и сооружения | G70: лет | H70: 12
C71: Оборудование | G71: лет | H71: 5
C72: Транспорт | G72: лет | H72: 10
B74: Ремонтатная программа оборудования
C75: Кумулятивный объем производства | G75: т | K75: 75000 | L75: 150000 | M75: 225000 | N75: 300000 | O75: 350000 | P75: 425000 | Q75: 500000 | R75: 575000 | S75: 650000 | T75: 700000 | U75: 775000 | V75: 850000 | W75: 925000 | X75: 1000000 | Y75: 1075000 | Z75: 1150000 | AA75: 1225000 | AB75: 1300000
C76: Вид ремонта | G76: выбор | K76: ТР | L76: ТР | M76: ТР | N76: ТР | O76: СР | P76: ТР | Q76: ТР | R76: ТР | S76: ТР | T76: СР | U76: ТР | V76: ТР | W76: КР | X76: ТР | Y76: ТР | Z76: ТР | AA76: ТР | AB76: ТР
A78: PPI, (RUB) | B78: Расходы на ремонт оборудования
C79: ТР | G79: млн руб. | H79: 8.5
C80: СР | G80: млн руб. | H80: 15.3
C81: КР | G81: млн руб. | H81: 20.4
B83: Ремонтатная программа транспорта
C84: Кумулятивная наработка | G84: ч | K84: 9000 | L84: 18000 | M84: 27000 | N84: 36000 | O84: 45000 | P84: 54000 | Q84: 63000 | R84: 72000 | S84: 81000 | T84: 90000 | U84: 99000 | V84: 108000 | W84: 117000 | X84: 126000 | Y84: 135000 | Z84: 144000 | AA84: 153000 | AB84: 162000
C85: Вид ремонта | G85: выбор | K85: ТР | L85: ТР | M85: ТР | N85: ТР | O85: ТР | P85: СР | Q85: ТР | R85: КР | S85: ТР | T85: КР | U85: ТР | V85: ТР | W85: ТР | X85: ТР | Y85: ТР | Z85: СР | AA85: ТР | AB85: ТР
C86: Коэффициент использования ТС | G86: % | H86: 0.95
A88: PPI, (RUB) | B88: Расходы на ремонт транспорта
C89: ТР | G89: млн руб. | H89: 2.5
C90: СР | G90: млн руб. | H90: 4
C91: КР | G91: млн руб. | H91: 15
B93: Ремонтатная программа зданий и сооружений
C94: Количество лет эксплуатации | G94: лет | K94: 1 | L94: 2 | M94: 3 | N94: 4 | O94: 5 | P94: 6 | Q94: 7 | R94: 8 | S94: 9 | T94: 10 | U94: 11 | V94: 12 | W94: 13 | X94: 14 | Y94: 15 | Z94: 16 | AA94: 17 | AB94: 18
C95: Вид ремонта | G95: выбор | K95: ТР | L95: ТР | M95: ТР | N95: ТР | O95: СР | P95: КР | Q95: ТР | R95: ТР | S95: ТР | T95: КР | U95: ТР | V95: ТР | W95: ТР | X95: ТР | Y95: ТР | Z95: ТР | AA95: ТР | AB95: ТР
A97: CPI, (RUB) | B97: Расходы на ремонт зданий и сооружений
C98: ТР | G98: млн руб. | H98: 1.2
C99: СР | G99: млн руб. | H99: 2.5
C100: КР | G100: млн руб. | H100: 3.4
B102: Сумма лошадинных сил всех транспортных средств | G102: л.с. | H102: 1500
A104: CPI, (RUB) | B104: Кадастровая стоимость земельного участка | G104: млн руб. | H104: 0
B106: ПРОИЗВОДСТВЕННАЯ ПРОГРАММА И ЦЕНЫ РЕАЛИЗАЦИИ
B108: Номинальная производительность | G108: т/ч | H108: 10
B110: Количество смен | G110: кол. | H110: 2
B112: Продолжительность смены | G112: ч | H112: 11
B114: Потери в рамках норматива | G114: % | H114: 0.05
B116: Вес единицы продукции
C117: Кладочный раствор | G117: кг/шт | H117: 50
C118: Легкий кладочный раствор | G118: кг/шт | H118: 50
C119: Кладочный раствор для стеклоблоков | G119: кг/шт | H119: 50
C120: Клеевой раствор для плит и блоков изпенобетона | G120: кг/шт | H120: 25
B122: Разбивка по номеклатуре продукции, в % | K122: =YEAR(H12) -> 2026 | L122: =IF(K122<YEAR($H$14),K122+1,"") -> 2027 | M122: =IF(L122<YEAR($H$14),L122+1,"") -> 2028 | N122: =IF(M122<YEAR($H$14),M122+1,"") -> 2029 | O122: =IF(N122<YEAR($H$14),N122+1,"") -> 2030 | P122: =IF(O122<YEAR($H$14),O122+1,"") -> 2031 | Q122: =IF(P122<YEAR($H$14),P122+1,"") -> 2032 | R122: =IF(Q122<YEAR($H$14),Q122+1,"") -> 2033 | S122: =IF(R122<YEAR($H$14),R122+1,"") -> 2034 | ... AA122: =IF(Z122<YEAR($H$14),Z122+1,"")
C123: Кладочный раствор | G123: % | K123: 0.25 | L123: 0.25 | M123: 0.25 | N123: 0.25 | O123: 0.25 | P123: 0.25 | Q123: 0.25 | R123: 0.25 | S123: 0.25 | T123: 0.25 | U123: 0.25 | V123: 0.25 | W123: 0.25 | X123: 0.25 | Y123: 0.25 | Z123: 0.25
C124: Легкий кладочный раствор | G124: % | K124: 0.25 | L124: 0.25 | M124: 0.25 | N124: 0.25 | O124: 0.25 | P124: 0.25 | Q124: 0.25 | R124: 0.25 | S124: 0.25 | T124: 0.25 | U124: 0.25 | V124: 0.25 | W124: 0.25 | X124: 0.25 | Y124: 0.25 | Z124: 0.25
C125: Кладочный раствор для стеклоблоков | G125: % | K125: 0.25 | L125: 0.25 | M125: 0.25 | N125: 0.25 | O125: 0.25 | P125: 0.25 | Q125: 0.25 | R125: 0.25 | S125: 0.25 | T125: 0.25 | U125: 0.25 | V125: 0.25 | W125: 0.25 | X125: 0.25 | Y125: 0.25 | Z125: 0.25
C126: Клеевой раствор для плит и блоков изпенобетона | G126: % | K126: 0.25 | L126: 0.25 | M126: 0.25 | N126: 0.25 | O126: 0.25 | P126: 0.25 | Q126: 0.25 | R126: 0.25 | S126: 0.25 | T126: 0.25 | U126: 0.25 | V126: 0.25 | W126: 0.25 | X126: 0.25 | Y126: 0.25 | Z126: 0.25
K127: =SUM(K123:K126) -> 1 | L127: =SUM(L123:L126) -> 1 | M127: =SUM(M123:M126) -> 1 | N127: =SUM(N123:N126) -> 1 | O127: =SUM(O123:O126) -> 1 | P127: =SUM(P123:P126) -> 1 | Q127: =SUM(Q123:Q126) -> 1 | R127: =SUM(R123:R126) -> 1 | ... AA127: =SUM(AA123:AA126) -> 0
A129: CPI, (RUB) | B129: Цены реализации продукции
C130: Кладочный раствор | G130: руб./т | H130: 10699
C131: Легкий кладочный раствор | G131: руб./т | H131: 5789
...

Sheet Расчеты
B1: =Title!$C$16 -> Строительство производства сухих строительных смесей
B2: =Title!$C$15 -> Финансово-экономическая модель | L2: {=Input!L2:L4} -> 45292 | M2: {=Input!M2:M4} -> 45658 | N2: {=Input!N2:N4} -> 46023 | O2: {=Input!O2:O4} -> 46388 | P2: {=Input!P2:P4} -> 46753 | Q2: {=Input!Q2:Q4} -> 47119 | R2: {=Input!R2:R4} -> 47484 | S2: {=Input!S2:S4} -> 47849 | ... AN2: {=Input!AN2:AN4}
B3: Расчеты | L3: 45657 | M3: 46022 | N3: 46387 | O3: 46752 | P3: 47118 | Q3: 47483 | R3: 47848 | S3: 48213 | T3: 48579 | U3: 48944 | V3: 49309 | W3: 49674 | X3: 50040 | Y3: 50405 | Z3: 50770 | AA3: 51135 | AB3: 51501 | AC3: 51866
L4: Факт | M4: Прогноз | N4: Прогноз | O4: Прогноз | P4: Прогноз | Q4: Прогноз | R4: Прогноз | S4: Прогноз | T4: Прогноз | U4: Прогноз | V4: Прогноз | W4: Прогноз | X4: Прогноз | Y4: Прогноз | Z4: Прогноз | AA4: Прогноз | AB4: Прогноз | AC4: Прогноз
H5: Ед. измерения | I5: Значение/База/Сумма
C7: ВРЕМЕННЫЕ ПАРАМЕТРЫ ПРОЕКТА
C9: Год | H9: х | L9: =IFERROR(YEAR(L3),"") -> 2024 | M9: =IFERROR(YEAR(M3),"") -> 2025 | N9: =IFERROR(YEAR(N3),"") -> 2026 | O9: =IFERROR(YEAR(O3),"") -> 2027 | P9: =IFERROR(YEAR(P3),"") -> 2028 | Q9: =IFERROR(YEAR(Q3),"") -> 2029 | R9: =IFERROR(YEAR(R3),"") -> 2030 | S9: =IFERROR(YEAR(S3),"") -> 2031 | ... AN9: =IFERROR(YEAR(AN3),"")
C10: Индекс операционной деятельности | H10: х | L10: =IF(L9=YEAR(Input!$H$12),YEARFRAC(Input!$H$12,Расчеты!L3),IF(Расчеты!L9=YEAR(Input!$H$14),YEARFRAC(Расчеты!L2,Input!$H$14),IF(AND(Расчеты!L9>YEAR(Input!$H$12),Расчеты!L9<YEAR(Input!$H$14)),1,0))) -> 0 | M10: =IF(M9=YEAR(Input!$H$12),YEARFRAC(Input!$H$12,Расчеты!M3),IF(Расчеты!M9=YEAR(Input!$H$14),YEARFRAC(Расчеты!M2,Input!$H$14),IF(AND(Расчеты!M9>YEAR(Input!$H$12),Расчеты!M9<YEAR(Input!$H$14)),1,0))) -> 0 | N10: =IF(N9=YEAR(Input!$H$12),YEARFRAC(Input!$H$12,Расчеты!N3),IF(Расчеты!N9=YEAR(Input!$H$14),YEARFRAC(Расчеты!N2,Input!$H$14),IF(AND(Расчеты!N9>YEAR(Input!$H$12),Расчеты!N9<YEAR(Input!$H$14)),1,0))) -> 0.83333333 | O10: =IF(O9=YEAR(Input!$H$12),YEARFRAC(Input!$H$12,Расчеты!O3),IF(Расчеты!O9=YEAR(Input!$H$14),YEARFRAC(Расчеты!O2,Input!$H$14),IF(AND(Расчеты!O9>YEAR(Input!$H$12),Расчеты!O9<YEAR(Input!$H$14)),1,0))) -> 1 | P10: =IF(P9=YEAR(Input!$H$12),YEARFRAC(Input!$H$12,Расчеты!P3),IF(Расчеты!P9=YEAR(Input!$H$14),YEARFRAC(Расчеты!P2,Input!$H$14),IF(AND(Расчеты!P9>YEAR(Input!$H$12),Расчеты!P9<YEAR(Input!$H$14)),1,0))) -> 1 | Q10: =IF(Q9=YEAR(Input!$H$12),YEARFRAC(Input!$H$12,Расчеты!Q3),IF(Расчеты!Q9=YEAR(Input!$H$14),YEARFRAC(Расчеты!Q2,Input!$H$14),IF(AND(Расчеты!Q9>YEAR(Input!$H$12),Расчеты!Q9<YEAR(Input!$H$14)),1,0))) -> 1 | R10: =IF(R9=YEAR(Input!$H$12),YEARFRAC(Input!$H$12,Расчеты!R3),IF(Расчеты!R9=YEAR(Input!$H$14),YEARFRAC(Расчеты!R2,Input!$H$14),IF(AND(Расчеты!R9>YEAR(Input!$H$12),Расчеты!R9<YEAR(Input!$H$14)),1,0))) -> 1 | S10: =IF(S9=YEAR(Input!$H$12),YEARFRAC(Input!$H$12,Расчеты!S3),IF(Расчеты!S9=YEAR(Input!$H$14),YEARFRAC(Расчеты!S2,Input!$H$14),IF(AND(Расчеты!S9>YEAR(Input!$H$12),Расчеты!S9<YEAR(Input!$H$14)),1,0))) -> 1 | ... AN10: =IF(AN9=YEAR(Input!$H$12),YEARFRAC(Input!$H$12,Расчеты!AN3),IF(Расчеты!AN9=YEAR(Input!$H$14),YEARFRAC(Расчеты!AN2,Input!$H$14),IF(AND(Расчеты!AN9>YEAR(Input!$H$12),Расчеты!AN9<YEAR(Input!$H$14)),1,0))) -> 0
C11: Количество месяцев операционной деятельности | H11: х | L11: =L10*12 -> 0 | M11: =M10*12 -> 0 | N11: =N10*12 -> 10 | O11: =O10*12 -> 12 | P11: =P10*12 -> 12 | Q11: =Q10*12 -> 12 | R11: =R10*12 -> 12 | S11: =S10*12 -> 12 | ... AN11: =AN10*12 -> 0
C12: Индекс операционной деятельности после оптимизации состава продукции | H12: х | L12: =IF(L9=YEAR(Input!$H$16),YEARFRAC(Input!$H$16,Расчеты!L3),IF(Расчеты!L9=YEAR(Input!$H$14),1,IF(AND(Расчеты!L9>YEAR(Input!$H$16),Расчеты!L9<YEAR(Input!$H$14)),1,0))) -> 0 | M12: =IF(M9=YEAR(Input!$H$16),YEARFRAC(Input!$H$16,Расчеты!M3),IF(Расчеты!M9=YEAR(Input!$H$14),1,IF(AND(Расчеты!M9>YEAR(Input!$H$16),Расчеты!M9<YEAR(Input!$H$14)),1,0))) -> 0 | N12: =IF(N9=YEAR(Input!$H$16),YEARFRAC(Input!$H$16,Расчеты!N3),IF(Расчеты!N9=YEAR(Input!$H$14),1,IF(AND(Расчеты!N9>YEAR(Input!$H$16),Расчеты!N9<YEAR(Input!$H$14)),1,0))) -> 0 | O12: =IF(O9=YEAR(Input!$H$16),YEARFRAC(Input!$H$16,Расчеты!O3),IF(Расчеты!O9=YEAR(Input!$H$14),1,IF(AND(Расчеты!O9>YEAR(Input!$H$16),Расчеты!O9<YEAR(Input!$H$14)),1,0))) -> 0 | P12: =IF(P9=YEAR(Input!$H$16),YEARFRAC(Input!$H$16,Расчеты!P3),IF(Расчеты!P9=YEAR(Input!$H$14),1,IF(AND(Расчеты!P9>YEAR(Input!$H$16),Расчеты!P9<YEAR(Input!$H$14)),1,0))) -> 0 | Q12: =IF(Q9=YEAR(Input!$H$16),YEARFRAC(Input!$H$16,Расчеты!Q3),IF(Расчеты!Q9=YEAR(Input!$H$14),1,IF(AND(Расчеты!Q9>YEAR(Input!$H$16),Расчеты!Q9<YEAR(Input!$H$14)),1,0))) -> 0 | R12: =IF(R9=YEAR(Input!$H$16),YEARFRAC(Input!$H$16,Расчеты!R3),IF(Расчеты!R9=YEAR(Input!$H$14),1,IF(AND(Расчеты!R9>YEAR(Input!$H$16),Расчеты!R9<YEAR(Input!$H$14)),1,0))) -> 0 | S12: =IF(S9=YEAR(Input!$H$16),YEARFRAC(Input!$H$16,Расчеты!S3),IF(Расчеты!S9=YEAR(Input!$H$14),1,IF(AND(Расчеты!S9>YEAR(Input!$H$16),Расчеты!S9<YEAR(Input!$H$14)),1,0))) -> 0 | ... AN12: =IF(AN9=YEAR(Input!$H$16),YEARFRAC(Input!$H$16,Расчеты!AN3),IF(Расчеты!AN9=YEAR(Input!$H$14),1,IF(AND(Расчеты!AN9>YEAR(Input!$H$16),Расчеты!AN9<YEAR(Input!$H$14)),1,0))) -> 0
C13: Индекс операционной деятельности до оптимизации состава продукции | H13: х | L13: =IF(AND(L9>=YEAR(Input!$H$12),L9<YEAR(Input!$H$16)),1,IF(L9=YEAR(Input!$H$16),YEARFRAC(Расчеты!L2,Input!$H$16,3),0)) -> 0 | M13: =IF(AND(M9>=YEAR(Input!$H$12),M9<YEAR(Input!$H$16)),1,IF(M9=YEAR(Input!$H$16),YEARFRAC(Расчеты!M2,Input!$H$16,3),0)) -> 0 | N13: =IF(AND(N9>=YEAR(Input!$H$12),N9<YEAR(Input!$H$16)),1,IF(N9=YEAR(Input!$H$16),YEARFRAC(Расчеты!N2,Input!$H$16,3),0)) -> 1 | O13: =IF(AND(O9>=YEAR(Input!$H$12),O9<YEAR(Input!$H$16)),1,IF(O9=YEAR(Input!$H$16),YEARFRAC(Расчеты!O2,Input!$H$16,3),0)) -> 1 | P13: =IF(AND(P9>=YEAR(Input!$H$12),P9<YEAR(Input!$H$16)),1,IF(P9=YEAR(Input!$H$16),YEARFRAC(Расчеты!P2,Input!$H$16,3),0)) -> 1 | Q13: =IF(AND(Q9>=YEAR(Input!$H$12),Q9<YEAR(Input!$H$16)),1,IF(Q9=YEAR(Input!$H$16),YEARFRAC(Расчеты!Q2,Input!$H$16,3),0)) -> 1 | R13: =IF(AND(R9>=YEAR(Input!$H$12),R9<YEAR(Input!$H$16)),1,IF(R9=YEAR(Input!$H$16),YEARFRAC(Расчеты!R2,Input!$H$16,3),0)) -> 1 | S13: =IF(AND(S9>=YEAR(Input!$H$12),S9<YEAR(Input!$H$16)),1,IF(S9=YEAR(Input!$H$16),YEARFRAC(Расчеты!S2,Input!$H$16,3),0)) -> 1 | ... AN13: =IF(AND(AN9>=YEAR(Input!$H$12),AN9<YEAR(Input!$H$16)),1,IF(AN9=YEAR(Input!$H$16),YEARFRAC(Расчеты!AN2,Input!$H$16,3),0)) -> 0
C14: Количество дней в году | H14: х | L14: =IFERROR(L3-L2+1,"") -> 366 | M14: =IFERROR(M3-M2+1,"") -> 365 | N14: =IFERROR(N3-N2+1,"") -> 365 | O14: =IFERROR(O3-O2+1,"") -> 365 | P14: =IFERROR(P3-P2+1,"") -> 366 | Q14: =IFERROR(Q3-Q2+1,"") -> 365 | R14: =IFERROR(R3-R2+1,"") -> 365 | S14: =IFERROR(S3-S2+1,"") -> 365 | ... AN14: =IFERROR(AN3-AN2+1,"")
C15: Количество часов в году | H15: х | L15: =IFERROR(L14*24,"") -> 8784 | M15: =IFERROR(M14*24,"") -> 8760 | N15: =IFERROR(N14*24,"") -> 8760 | O15: =IFERROR(O14*24,"") -> 8760 | P15: =IFERROR(P14*24,"") -> 8784 | Q15: =IFERROR(Q14*24,"") -> 8760 | R15: =IFERROR(R14*24,"") -> 8760 | S15: =IFERROR(S14*24,"") -> 8760 | ... AN15: =IFERROR(AN14*24,"")
C16: Количество лет операционной деятельности | H16: х | L16: =IF(L9=YEAR(Input!$H$12),1,IF(AND(Расчеты!L9>YEAR(Input!$H$12),Расчеты!L9<=YEAR(Input!$H$14)),Расчеты!K16+1,0)) -> 0 | M16: =IF(M9=YEAR(Input!$H$12),1,IF(AND(Расчеты!M9>YEAR(Input!$H$12),Расчеты!M9<=YEAR(Input!$H$14)),Расчеты!L16+1,0)) -> 0 | N16: =IF(N9=YEAR(Input!$H$12),1,IF(AND(Расчеты!N9>YEAR(Input!$H$12),Расчеты!N9<=YEAR(Input!$H$14)),Расчеты!M16+1,0)) -> 1 | O16: =IF(O9=YEAR(Input!$H$12),1,IF(AND(Расчеты!O9>YEAR(Input!$H$12),Расчеты!O9<=YEAR(Input!$H$14)),Расчеты!N16+1,0)) -> 2 | P16: =IF(P9=YEAR(Input!$H$12),1,IF(AND(Расчеты!P9>YEAR(Input!$H$12),Расчеты!P9<=YEAR(Input!$H$14)),Расчеты!O16+1,0)) -> 3 | Q16: =IF(Q9=YEAR(Input!$H$12),1,IF(AND(Расчеты!Q9>YEAR(Input!$H$12),Расчеты!Q9<=YEAR(Input!$H$14)),Расчеты!P16+1,0)) -> 4 | R16: =IF(R9=YEAR(Input!$H$12),1,IF(AND(Расчеты!R9>YEAR(Input!$H$12),Расчеты!R9<=YEAR(Input!$H$14)),Расчеты!Q16+1,0)) -> 5 | S16: =IF(S9=YEAR(Input!$H$12),1,IF(AND(Расчеты!S9>YEAR(Input!$H$12),Расчеты!S9<=YEAR(Input!$H$14)),Расчеты!R16+1,0)) -> 6 | ... AN16: =IF(AN9=YEAR(Input!$H$12),1,IF(AND(Расчеты!AN9>YEAR(Input!$H$12),Расчеты!AN9<=YEAR(Input!$H$14)),Расчеты!AM16+1,0)) -> 0
C17: Флаг дисконтирования | H17: х | L17: =IF(OR(L9<YEAR(Input!$H$10),L9>YEAR(Input!$H$14)),0,1) -> 0 | M17: =IF(OR(M9<YEAR(Input!$H$10),M9>YEAR(Input!$H$14)),0,1) -> 1 | N17: =IF(OR(N9<YEAR(Input!$H$10),N9>YEAR(Input!$H$14)),0,1) -> 1 | O17: =IF(OR(O9<YEAR(Input!$H$10),O9>YEAR(Input!$H$14)),0,1) -> 1 | P17: =IF(OR(P9<YEAR(Input!$H$10),P9>YEAR(Input!$H$14)),0,1) -> 1 | Q17: =IF(OR(Q9<YEAR(Input!$H$10),Q9>YEAR(Input!$H$14)),0,1) -> 1 | R17: =IF(OR(R9<YEAR(Input!$H$10),R9>YEAR(Input!$H$14)),0,1) -> 1 | S17: =IF(OR(S9<YEAR(Input!$H$10),S9>YEAR(Input!$H$14)),0,1) -> 1 | ... AN17: =IF(OR(AN9<YEAR(Input!$H$10),AN9>YEAR(Input!$H$14)),0,1) -> 0
C19: ФЛАГИ ПРОВЕДЕНИЯ РЕМОНТОВ
C21: Флаг проведения текущего ремонта оборудования | H21: х | L21: =IFERROR(IF(AND((INDEX($L$119:$AC$119,MATCH(L$423,$L$118:$AC$118,1)))="ТР",K$423<INDEX($L$118:$AC$118,MATCH(L$423,$L$118:$AC$118,1))),1,0),0) -> 0 | M21: =IFERROR(IF(AND((INDEX($L$119:$AC$119,MATCH(M$423,$L$118:$AC$118,1)))="ТР",L$423<INDEX($L$118:$AC$118,MATCH(M$423,$L$118:$AC$118,1))),1,0),0) -> 0 | N21: =IFERROR(IF(AND((INDEX($L$119:$AC$119,MATCH(N$423,$L$118:$AC$118,1)))="ТР",M$423<INDEX($L$118:$AC$118,MATCH(N$423,$L$118:$AC$118,1))),1,0),0) -> 0 | O21: =IFERROR(IF(AND((INDEX($L$119:$AC$119,MATCH(O$423,$L$118:$AC$118,1)))="ТР",N$423<INDEX($L$118:$AC$118,MATCH(O$423,$L$118:$AC$118,1))),1,0),0) -> 1 | P21: =IFERROR(IF(AND((INDEX($L$119:$AC$119,MATCH(P$423,$L$118:$AC$118,1)))="ТР",O$423<INDEX($L$118:$AC$118,MATCH(P$423,$L$118:$AC$118,1))),1,0),0) -> 1 | Q21: =IFERROR(IF(AND((INDEX($L$119:$AC$119,MATCH(Q$423,$L$118:$AC$118,1)))="ТР",P$423<INDEX($L$118:$AC$118,MATCH(Q$423,$L$118:$AC$118,1))),1,0),0) -> 1 | R21: =IFERROR(IF(AND((INDEX($L$119:$AC$119,MATCH(R$423,$L$118:$AC$118,1)))="ТР",Q$423<INDEX($L$118:$AC$118,MATCH(R$423,$L$118:$AC$118,1))),1,0),0) -> 0 | S21: =IFERROR(IF(AND((INDEX($L$119:$AC$119,MATCH(S$423,$L$118:$AC$118,1)))="ТР",R$423<INDEX($L$118:$AC$118,MATCH(S$423,$L$118:$AC$118,1))),1,0),0) -> 1 | ... AN21: =IFERROR(IF(AND((INDEX($L$119:$AC$119,MATCH(AN$423,$L$118:$AC$118,1)))="ТР",AM$423<INDEX($L$118:$AC$118,MATCH(AN$423,$L$118:$AC$118,1))),1,0),0) -> 0
C22: Флаг проведения среднего ремонта оборудования | H22: х | L22: =IFERROR(IF(AND((INDEX($L$119:$AC$119,MATCH(L$423,$L$118:$AC$118,1)))="СР",K$423<INDEX($L$118:$AC$118,MATCH(L$423,$L$118:$AC$118,1))),1,0),0) -> 0 | M22: =IFERROR(IF(AND((INDEX($L$119:$AC$119,MATCH(M$423,$L$118:$AC$118,1)))="СР",L$423<INDEX($L$118:$AC$118,MATCH(M$423,$L$118:$AC$118,1))),1,0),0) -> 0 | N22: =IFERROR(IF(AND((INDEX($L$119:$AC$119,MATCH(N$423,$L$118:$AC$118,1)))="СР",M$423<INDEX($L$118:$AC$118,MATCH(N$423,$L$118:$AC$118,1))),1,0),0) -> 0 | O22: =IFERROR(IF(AND((INDEX($L$119:$AC$119,MATCH(O$423,$L$118:$AC$118,1)))="СР",N$423<INDEX($L$118:$AC$118,MATCH(O$423,$L$118:$AC$118,1))),1,0),0) -> 0 | P22: =IFERROR(IF(AND((INDEX($L$119:$AC$119,MATCH(P$423,$L$118:$AC$118,1)))="СР",O$423<INDEX($L$118:$AC$118,MATCH(P$423,$L$118:$AC$118,1))),1,0),0) -> 0 | Q22: =IFERROR(IF(AND((INDEX($L$119:$AC$119,MATCH(Q$423,$L$118:$AC$118,1)))="СР",P$423<INDEX($L$118:$AC$118,MATCH(Q$423,$L$118:$AC$118,1))),1,0),0) -> 0 | R22: =IFERROR(IF(AND((INDEX($L$119:$AC$119,MATCH(R$423,$L$118:$AC$118,1)))="СР",Q$423<INDEX($L$118:$AC$118,MATCH(R$423,$L$118:$AC$118,1))),1,0),0) -> 1 | S22: =IFERROR(IF(AND((INDEX($L$119:$AC$119,MATCH(S$423,$L$118:$AC$118,1)))="СР",R$423<INDEX($L$118:$AC$118,MATCH(S$423,$L$118:$AC$118,1))),1,0),0) -> 0 | ... AN22: =IFERROR(IF(AND((INDEX($L$119:$AC$119,MATCH(AN$423,$L$118:$AC$118,1)))="СР",AM$423<INDEX($L$118:$AC$118,MATCH(AN$423,$L$118:$AC$118,1))),1,0),0) -> 0
C23: Флаг проведения капитального ремонта оборудования | H23: х | L23: =IFERROR(IF(AND((INDEX($L$119:$AC$119,MATCH(L$423,$L$118:$AC$118,1)))="КР",K$423<INDEX($L$118:$AC$118,MATCH(L$423,$L$118:$AC$118,1))),1,0),0) -> 0 | M23: =IFERROR(IF(AND((INDEX($L$119:$AC$119,MATCH(M$423,$L$118:$AC$118,1)))="КР",L$423<INDEX($L$118:$AC$118,MATCH(M$423,$L$118:$AC$118,1))),1,0),0) -> 0 | N23: =IFERROR(IF(AND((INDEX($L$119:$AC$119,MATCH(N$423,$L$118:$AC$118,1)))="КР",M$423<INDEX($L$118:$AC$118,MATCH(N$423,$L$118:$AC$118,1))),1,0),0) -> 0 | O23: =IFERROR(IF(AND((INDEX($L$119:$AC$119,MATCH(O$423,$L$118:$AC$118,1)))="КР",N$423<INDEX($L$118:$AC$118,MATCH(O$423,$L$118:$AC$118,1))),1,0),0) -> 0 | P23: =IFERROR(IF(AND((INDEX($L$119:$AC$119,MATCH(P$423,$L$118:$AC$118,1)))="КР",O$423<INDEX($L$118:$AC$118,MATCH(P$423,$L$118:$AC$118,1))),1,0),0) -> 0 | Q23: =IFERROR(IF(AND((INDEX($L$119:$AC$119,MATCH(Q$423,$L$118:$AC$118,1)))="КР",P$423<INDEX($L$118:$AC$118,MATCH(Q$423,$L$118:$AC$118,1))),1,0),0) -> 0 | R23: =IFERROR(IF(AND((INDEX($L$119:$AC$119,MATCH(R$423,$L$118:$AC$118,1)))="КР",Q$423<INDEX($L$118:$AC$118,MATCH(R$423,$L$118:$AC$118,1))),1,0),0) -> 0 | S23: =IFERROR(IF(AND((INDEX($L$119:$AC$119,MATCH(S$423,$L$118:$AC$118,1)))="КР",R$423<INDEX($L$118:$AC$118,MATCH(S$423,$L$118:$AC$118,1))),1,0),0) -> 0 | ... AN23: =IFERROR(IF(AND((INDEX($L$119:$AC$119,MATCH(AN$423,$L$118:$AC$118,1)))="КР",AM$423<INDEX($L$118:$AC$118,MATCH(AN$423,$L$118:$AC$118,1))),1,0),0) -> 0
C24: Флаг проведения текущего ремонта транспорта | H24: х | L24: =IFERROR(IF(AND((INDEX($L$129:$AC$129,MATCH(L$131,$L$128:$AC$128,1)))="ТР",K$131<INDEX($L$128:$AC$128,MATCH(L$131,$L$128:$AC$128,1))),1,0),0) -> 0 | M24: =IFERROR(IF(AND((INDEX($L$129:$AC$129,MATCH(M$131,$L$128:$AC$128,1)))="ТР",L$131<INDEX($L$128:$AC$128,MATCH(M$131,$L$128:$AC$128,1))),1,0),0) -> 0 | N24: =IFERROR(IF(AND((INDEX($L$129:$AC$129,MATCH(N$131,$L$128:$AC$128,1)))="ТР",M$131<INDEX($L$128:$AC$128,MATCH(N$131,$L$128:$AC$128,1))),1,0),0) -> 0 | O24: =IFERROR(IF(AND((INDEX($L$129:$AC$129,MATCH(O$131,$L$128:$AC$128,1)))="ТР",N$131<INDEX($L$128:$AC$128,MATCH(O$131,$L$128:$AC$128,1))),1,0),0) -> 1 | P24: =IFERROR(IF(AND((INDEX($L$129:$AC$129,MATCH(P$131,$L$128:$AC$128,1)))="ТР",O$131<INDEX($L$128:$AC$128,MATCH(P$131,$L$128:$AC$128,1))),1,0),0) -> 1 | Q24: =IFERROR(IF(AND((INDEX($L$129:$AC$129,MATCH(Q$131,$L$128:$AC$128,1)))="ТР",P$131<INDEX($L$128:$AC$128,MATCH(Q$131,$L$128:$AC$128,1))),1,0),0) -> 1 | R24: =IFERROR(IF(AND((INDEX($L$129:$AC$129,MATCH(R$131,$L$128:$AC$128,1)))="ТР",Q$131<INDEX($L$128:$AC$128,MATCH(R$131,$L$128:$AC$128,1))),1,0),0) -> 1 | S24: =IFERROR(IF(AND((INDEX($L$129:$AC$129,MATCH(S$131,$L$128:$AC$128,1)))="ТР",R$131<INDEX($L$128:$AC$128,MATCH(S$131,$L$128:$AC$128,1))),1,0),0) -> 1 | ... AN24: =IFERROR(IF(AND((INDEX($L$129:$AC$129,MATCH(AN$131,$L$128:$AC$128,1)))="ТР",AM$131<INDEX($L$128:$AC$128,MATCH(AN$131,$L$128:$AC$128,1))),1,0),0) -> 0
C25: Флаг проведения среднего ремонта транспорта | H25: х | L25: =IFERROR(IF(AND((INDEX($L$129:$AC$129,MATCH(L$131,$L$128:$AC$128,1)))="СР",K$131<INDEX($L$128:$AC$128,MATCH(L$131,$L$128:$AC$128,1))),1,0),0) -> 0 | M25: =IFERROR(IF(AND((INDEX($L$129:$AC$129,MATCH(M$131,$L$128:$AC$128,1)))="СР",L$131<INDEX($L$128:$AC$128,MATCH(M$131,$L$128:$AC$128,1))),1,0),0) -> 0 | N25: =IFERROR(IF(AND((INDEX($L$129:$AC$129,MATCH(N$131,$L$128:$AC$128,1)))="СР",M$131<INDEX($L$128:$AC$128,MATCH(N$131,$L$128:$AC$128,1))),1,0),0) -> 0 | O25: =IFERROR(IF(AND((INDEX($L$129:$AC$129,MATCH(O$131,$L$128:$AC$128,1)))="СР",N$131<INDEX($L$128:$AC$128,MATCH(O$131,$L$128:$AC$128,1))),1,0),0) -> 0 | P25: =IFERROR(IF(AND((INDEX($L$129:$AC$129,MATCH(P$131,$L$128:$AC$128,1)))="СР",O$131<INDEX($L$128:$AC$128,MATCH(P$131,$L$128:$AC$128,1))),1,0),0) -> 0 | Q25: =IFERROR(IF(AND((INDEX($L$129:$AC$129,MATCH(Q$131,$L$128:$AC$128,1)))="СР",P$131<INDEX($L$128:$AC$128,MATCH(Q$131,$L$128:$AC$128,1))),1,0),0) -> 0 | R25: =IFERROR(IF(AND((INDEX($L$129:$AC$129,MATCH(R$131,$L$128:$AC$128,1)))="СР",Q$131<INDEX($L$128:$AC$128,MATCH(R$131,$L$128:$AC$128,1))),1,0),0) -> 0 | S25: =IFERROR(IF(AND((INDEX($L$129:$AC$129,MATCH(S$131,$L$128:$AC$128,1)))="СР",R$131<INDEX($L$128:$AC$128,MATCH(S$131,$L$128:$AC$128,1))),1,0),0) -> 0 | ... AN25: =IFERROR(IF(AND((INDEX($L$129:$AC$129,MATCH(AN$131,$L$128:$AC$128,1)))="СР",AM$131<INDEX($L$128:$AC$128,MATCH(AN$131,$L$128:$AC$128,1))),1,0),0) -> 0
C26: Флаг проведения капитального ремонта транспорта | H26: х | L26: =IFERROR(IF(AND((INDEX($L$129:$AC$129,MATCH(L$131,$L$128:$AC$128,1)))="КР",K$131<INDEX($L$128:$AC$128,MATCH(L$131,$L$128:$AC$128,1))),1,0),0) -> 0 | M26: =IFERROR(IF(AND((INDEX($L$129:$AC$129,MATCH(M$131,$L$128:$AC$128,1)))="КР",L$131<INDEX($L$128:$AC$128,MATCH(M$131,$L$128:$AC$128,1))),1,0),0) -> 0 | N26: =IFERROR(IF(AND((INDEX($L$129:$AC$129,MATCH(N$131,$L$128:$AC$128,1)))="КР",M$131<INDEX($L$128:$AC$128,MATCH(N$131,$L$128:$AC$128,1))),1,0),0) -> 0 | O26: =IFERROR(IF(AND((INDEX($L$129:$AC$129,MATCH(O$131,$L$128:$AC$128,1)))="КР",N$131<INDEX($L$128:$AC$128,MATCH(O$131,$L$128:$AC$128,1))),1,0),0) -> 0 | P26: =IFERROR(IF(AND((INDEX($L$129:$AC$129,MATCH(P$131,$L$128:$AC$128,1)))="КР",O$131<INDEX($L$128:$AC$128,MATCH(P$131,$L$128:$AC$128,1))),1,0),0) -> 0 | Q26: =IFERROR(IF(AND((INDEX($L$129:$AC$129,MATCH(Q$131,$L$128:$AC$128,1)))="КР",P$131<INDEX($L$128:$AC$128,MATCH(Q$131,$L$128:$AC$128,1))),1,0),0) -> 0 | R26: =IFERROR(IF(AND((INDEX($L$129:$AC$129,MATCH(R$131,$L$128:$AC$128,1)))="КР",Q$131<INDEX($L$128:$AC$128,MATCH(R$131,$L$128:$AC$128,1))),1,0),0) -> 0 | S26: =IFERROR(IF(AND((INDEX($L$129:$AC$129,MATCH(S$131,$L$128:$AC$128,1)))="КР",R$131<INDEX($L$128:$AC$128,MATCH(S$131,$L$128:$AC$128,1))),1,0),0) -> 0 | ... AN26: =IFERROR(IF(AND((INDEX($L$129:$AC$129,MATCH(AN$131,$L$128:$AC$128,1)))="КР",AM$131<INDEX($L$128:$AC$128,MATCH(AN$131,$L$128:$AC$128,1))),1,0),0) -> 0
C27: Флаг проведения текущего ремонта зданий и сооружений | H27: х | L27: =IFERROR(IF((INDEX($L$109:$AC$109,MATCH(L$16,$L$108:$AC$108,0)))="ТР",1,0),0) -> 0 | M27: =IFERROR(IF((INDEX($L$109:$AC$109,MATCH(M$16,$L$108:$AC$108,0)))="ТР",1,0),0) -> 0 | N27: =IFERROR(IF((INDEX($L$109:$AC$109,MATCH(N$16,$L$108:$AC$108,0)))="ТР",1,0),0) -> 1 | O27: =IFERROR(IF((INDEX($L$109:$AC$109,MATCH(O$16,$L$108:$AC$108,0)))="ТР",1,0),0) -> 1 | P27: =IFERROR(IF((INDEX($L$109:$AC$109,MATCH(P$16,$L$108:$AC$108,0)))="ТР",1,0),0) -> 1 | Q27: =IFERROR(IF((INDEX($L$109:$AC$109,MATCH(Q$16,$L$108:$AC$108,0)))="ТР",1,0),0) -> 1 | R27: =IFERROR(IF((INDEX($L$109:$AC$109,MATCH(R$16,$L$108:$AC$108,0)))="ТР",1,0),0) -> 0 | S27: =IFERROR(IF((INDEX($L$109:$AC$109,MATCH(S$16,$L$108:$AC$108,0)))="ТР",1,0),0) -> 0 | ... AN27: =IFERROR(IF((INDEX($L$109:$AC$109,MATCH(AN$16,$L$108:$AC$108,0)))="ТР",1,0),0) -> 0
C28: Флаг проведения среднего ремонта зданий и сооружений | H28: х | L28: =IFERROR(IF((INDEX($L$109:$AC$109,MATCH(L$16,$L$108:$AC$108,0)))="СР",1,0),0) -> 0 | M28: =IFERROR(IF((INDEX($L$109:$AC$109,MATCH(M$16,$L$108:$AC$108,0)))="СР",1,0),0) -> 0 | N28: =IFERROR(IF((INDEX($L$109:$AC$109,MATCH(N$16,$L$108:$AC$108,0)))="СР",1,0),0) -> 0 | O28: =IFERROR(IF((INDEX($L$109:$AC$109,MATCH(O$16,$L$108:$AC$108,0)))="СР",1,0),0) -> 0 | P28: =IFERROR(IF((INDEX($L$109:$AC$109,MATCH(P$16,$L$108:$AC$108,0)))="СР",1,0),0) -> 0 | Q28: =IFERROR(IF((INDEX($L$109:$AC$109,MATCH(Q$16,$L$108:$AC$108,0)))="СР",1,0),0) -> 0 | R28: =IFERROR(IF((INDEX($L$109:$AC$109,MATCH(R$16,$L$108:$AC$108,0)))="СР",1,0),0) -> 1 | S28: =IFERROR(IF((INDEX($L$109:$AC$109,MATCH(S$16,$L$108:$AC$108,0)))="СР",1,0),0) -> 0 | ... AN28: =IFERROR(IF((INDEX($L$109:$AC$109,MATCH(AN$16,$L$108:$AC$108,0)))="СР",1,0),0) -> 0
C29: Флаг проведения капитального ремонта зданий и сооружений | H29: х | L29: =IFERROR(IF((INDEX($L$109:$AC$109,MATCH(L$16,$L$108:$AC$108,0)))="КР",1,0),0) -> 0 | M29: =IFERROR(IF((INDEX($L$109:$AC$109,MATCH(M$16,$L$108:$AC$108,0)))="КР",1,0),0) -> 0 | N29: =IFERROR(IF((INDEX($L$109:$AC$109,MATCH(N$16,$L$108:$AC$108,0)))="КР",1,0),0) -> 0 | O29: =IFERROR(IF((INDEX($L$109:$AC$109,MATCH(O$16,$L$108:$AC$108,0)))="КР",1,0),0) -> 0 | P29: =IFERROR(IF((INDEX($L$109:$AC$109,MATCH(P$16,$L$108:$AC$108,0)))="КР",1,0),0) -> 0 | Q29: =IFERROR(IF((INDEX($L$109:$AC$109,MATCH(Q$16,$L$108:$AC$108,0)))="КР",1,0),0) -> 0 | R29: =IFERROR(IF((INDEX($L$109:$AC$109,MATCH(R$16,$L$108:$AC$108,0)))="КР",1,0),0) -> 0 | S29: =IFERROR(IF((INDEX($L$109:$AC$109,MATCH(S$16,$L$108:$AC$108,0)))="КР",1,0),0) -> 1 | ... AN29: =IFERROR(IF((INDEX($L$109:$AC$109,MATCH(AN$16,$L$108:$AC$108,0)))="КР",1,0),0) -> 0
C31: НАЛОГОВОЕ ОКРУЖЕНИЕ ПРОЕКТА
C33: =Input!B31 -> Доля прибыли к зачету против убытков | H33: % | L33: =Input!L31 -> 0.5 | M33: =Input!M31 -> 0.5 | N33: =Input!N31 -> 0.5 | O33: =Input!O31 -> 0.5 | P33: =Input!P31 -> 0.5 | Q33: =Input!Q31 -> 0.5 | R33: =Input!R31 -> 0.5 | S33: =Input!S31 -> 0.5 | ... AN33: =Input!AN31 -> 0
C34: =Input!B32 -> НДС | H34: % | L34: =Input!L32 -> 0.2 | M34: =Input!M32 -> 0.2 | N34: =Input!N32 -> 0.2 | O34: =Input!O32 -> 0.2 | P34: =Input!P32 -> 0.2 | Q34: =Input!Q32 -> 0.2 | R34: =Input!R32 -> 0.2 | S34: =Input!S32 -> 0.2 | ... AN34: =Input!AN32 -> 0
C35: =Input!B33 -> Ставка налога на прибыль | H35: % | L35: =Input!L33 -> 0.2 | M35: =Input!M33 -> 0.25 | N35: =Input!N33 -> 0.25 | O35: =Input!O33 -> 0.25 | P35: =Input!P33 -> 0.25 | Q35: =Input!Q33 -> 0.25 | R35: =Input!R33 -> 0.25 | S35: =Input!S33 -> 0.25 | ... AN35: =Input!AN33 -> 0
C36: =Input!B34 -> Ставка налога на имущество | H36: % | L36: =Input!L34 -> 0.022 | M36: =Input!M34 -> 0.022 | N36: =Input!N34 -> 0.022 | O36: =Input!O34 -> 0.022 | P36: =Input!P34 -> 0.022 | Q36: =Input!Q34 -> 0.022 | R36: =Input!R34 -> 0.022 | S36: =Input!S34 -> 0.022 | ... AN36: =Input!AN34 -> 0
C37: =Input!B35 -> Ставка налога на землю | H37: % | L37: =Input!L35 -> 0.015 | M37: =Input!M35 -> 0.015 | N37: =Input!N35 -> 0.015 | O37: =Input!O35 -> 0.015 | P37: =Input!P35 -> 0.015 | Q37: =Input!Q35 -> 0.015 | R37: =Input!R35 -> 0.015 | S37: =Input!S35 -> 0.015 | ... AN37: =Input!AN35 -> 0
C38: =Input!B36 -> Ставка транспортного налога | H38: руб/л.с. | L38: =Input!L36 -> 2.5 | M38: =Input!M36 -> 2.5 | N38: =Input!N36 -> 2.5 | O38: =Input!O36 -> 2.5 | P38: =Input!P36 -> 2.5 | Q38: =Input!Q36 -> 2.5 | R38: =Input!R36 -> 2.5 | S38: =Input!S36 -> 2.5 | ... AN38: =Input!AN36 -> 0
C39: =Input!B37 -> Социальные отчисления (ПФР, ФСС, ФОМС) | H39: % | L39: =Input!L37 -> 0.302 | M39: =Input!M37 -> 0.302 | N39: =Input!N37 -> 0.302 | O39: =Input!O37 -> 0.302 | P39: =Input!P37 -> 0.302 | Q39: =Input!Q37 -> 0.302 | R39: =Input!R37 -> 0.302 | S39: =Input!S37 -> 0.302 | ... AN39: =Input!AN37 -> 0
C40: =Input!B38 -> Социальные отчисления от несчастных случаев и проф. заболеваний (рабочие) | H40: % | L40: =Input!L38 -> 0.08 | M40: =Input!M38 -> 0.08 | N40: =Input!N38 -> 0.08 | O40: =Input!O38 -> 0.08 | P40: =Input!P38 -> 0.08 | Q40: =Input!Q38 -> 0.08 | R40: =Input!R38 -> 0.08 | S40: =Input!S38 -> 0.08 | ... AN40: =Input!AN38 -> 0
C41: =Input!B39 -> Социальные отчисления от несчастных случаев и проф. заболеваний (служащие) | H41: % | L41: =Input!L39 -> 0.05 | M41: =Input!M39 -> 0.05 | N41: =Input!N39 -> 0.05 | O41: =Input!O39 -> 0.05 | P41: =Input!P39 -> 0.05 | Q41: =Input!Q39 -> 0.05 | R41: =Input!R39 -> 0.05 | S41: =Input!S39 -> 0.05 | ... AN41: =Input!AN39 -> 0
C43: МАКРОЭКОНОМИЧЕСКИЕ ПАРАМЕТРЫ ПРОЕКТА
C45: =Input!B21 -> Обменный курс рубля к доллару | H45: RUB/USD | L45: =Input!L21 -> 59 | M45: =Input!M21 -> 60 | N45: =Input!N21 -> 61 | O45: =Input!O21 -> 62 | P45: =Input!P21 -> 63 | Q45: =Input!Q21 -> 59 | R45: =Input!R21 -> 59 | S45: =Input!S21 -> 59 | ... AN45: =Input!AN21 -> 0
C46: Ключевая ставка ЦБ РФ | H46: % | L46: =Input!L27 -> 0.21 | M46: =Input!M27 -> 0.2 | N46: =Input!N27 -> 0.15 | O46: =Input!O27 -> 0.11 | P46: =Input!P27 -> 0.1 | Q46: =Input!Q27 -> 0.08 | R46: =Input!R27 -> 0.07 | S46: =Input!S27 -> 0.07 | ... AN46: =Input!AN27 -> 0
C48: Цепные индексы инфляции
C50: =Input!B22 -> CPI, (RUB) | H50: х | L50: =Input!L22 -> 1.04 | M50: =Input!M22 -> 1.04 | N50: =Input!N22 -> 1.04 | O50: =Input!O22 -> 1.04 | P50: =Input!P22 -> 1.04 | Q50: =Input!Q22 -> 1.04 | R50: =Input!R22 -> 1.04 | S50: =Input!S22 -> 1.04 | ... AN50: =Input!AN22 -> 0
C51: =Input!B23 -> PPI, (RUB) | H51: х | L51: =Input!L23 -> 1.04 | M51: =Input!M23 -> 1.04 | N51: =Input!N23 -> 1.04 | O51: =Input!O23 -> 1.04 | P51: =Input!P23 -> 1.04 | Q51: =Input!Q23 -> 1.04 | R51: =Input!R23 -> 1.04 | S51: =Input!S23 -> 1.04 | ... AN51: =Input!AN23 -> 0
C52: =Input!B24 -> PPI, (USD) | H52: х | L52: =Input!L24 -> 1.03 | M52: =Input!M24 -> 1.03 | N52: =Input!N24 -> 1.03 | O52: =Input!O24 -> 1.03 | P52: =Input!P24 -> 1.03 | Q52: =Input!Q24 -> 1.03 | R52: =Input!R24 -> 1.03 | S52: =Input!S24 -> 1.03 | ... AN52: =Input!AN24 -> 0
C53: =Input!B25 -> Индекс роста заработной платы (RUB) | H53: х | L53: =Input!L25 -> 1.04 | M53: =Input!M25 -> 1.04 | N53: =Input!N25 -> 1.04 | O53: =Input!O25 -> 1.04 | P53: =Input!P25 -> 1.04 | Q53: =Input!Q25 -> 1.04 | R53: =Input!R25 -> 1.04 | S53: =Input!S25 -> 1.04 | ... AN53: =Input!AN25 -> 0
C54: =Input!B26 -> Индекс роста цен на естественные монополии (электроэнергия) | H54: х | L54: =Input!L26 -> 1.05 | M54: =Input!M26 -> 1.05 | N54: =Input!N26 -> 1.05 | O54: =Input!O26 -> 1.05 | P54: =Input!P26 -> 1.05 | Q54: =Input!Q26 -> 1.05 | R54: =Input!R26 -> 1.05 | S54: =Input!S26 -> 1.05 | ... AN54: =Input!AN26 -> 0
C56: Базисные индексы инфляции индексы инфляции
C58: =Input!B22 -> CPI, (RUB) | H58: х | L58: =IF(L$9=Input!$H$9,1,Расчеты!L50*Расчеты!K58) -> 1 | M58: =IF(M$9=Input!$H$9,1,Расчеты!M50*Расчеты!L58) -> 1.04 | N58: =IF(N$9=Input!$H$9,1,Расчеты!N50*Расчеты!M58) -> 1.0816 | O58: =IF(O$9=Input!$H$9,1,Расчеты!O50*Расчеты!N58) -> 1.124864 | P58: =IF(P$9=Input!$H$9,1,Расчеты!P50*Расчеты!O58) -> 1.1698586 | Q58: =IF(Q$9=Input!$H$9,1,Расчеты!Q50*Расчеты!P58) -> 1.2166529 | R58: =IF(R$9=Input!$H$9,1,Расчеты!R50*Расчеты!Q58) -> 1.265319 | S58: =IF(S$9=Input!$H$9,1,Расчеты!S50*Расчеты!R58) -> 1.3159318 | ... AN58: =IF(AN$9=Input!$H$9,1,Расчеты!AN50*Расчеты!AM58) -> 0
C59: =Input!B23 -> PPI, (RUB) | H59: х | L59: =IF(L$9=Input!$H$9,1,Расчеты!L51*Расчеты!K59) -> 1 | M59: =IF(M$9=Input!$H$9,1,Расчеты!M51*Расчеты!L59) -> 1.04 | N59: =IF(N$9=Input!$H$9,1,Расчеты!N51*Расчеты!M59) -> 1.0816 | O59: =IF(O$9=Input!$H$9,1,Расчеты!O51*Расчеты!N59) -> 1.124864 | P59: =IF(P$9=Input!$H$9,1,Расчеты!P51*Расчеты!O59) -> 1.1698586 | Q59: =IF(Q$9=Input!$H$9,1,Расчеты!Q51*Расчеты!P59) -> 1.2166529 | R59: =IF(R$9=Input!$H$9,1,Расчеты!R51*Расчеты!Q59) -> 1.265319 | S59: =IF(S$9=Input!$H$9,1,Расчеты!S51*Расчеты!R59) -> 1.3159318 | ... AN59: =IF(AN$9=Input!$H$9,1,Расчеты!AN51*Расчеты!AM59) -> 0
C60: =Input!B24 -> PPI, (USD) | H60: х | L60: =IF(L$9=Input!$H$9,1,Расчеты!L52*Расчеты!K60) -> 1 | M60: =IF(M$9=Input!$H$9,1,Расчеты!M52*Расчеты!L60) -> 1.03 | N60: =IF(N$9=Input!$H$9,1,Расчеты!N52*Расчеты!M60) -> 1.0609 | O60: =IF(O$9=Input!$H$9,1,Расчеты!O52*Расчеты!N60) -> 1.092727 | P60: =IF(P$9=Input!$H$9,1,Расчеты!P52*Расчеты!O60) -> 1.1255088 | Q60: =IF(Q$9=Input!$H$9,1,Расчеты!Q52*Расчеты!P60) -> 1.1592741 | R60: =IF(R$9=Input!$H$9,1,Расчеты!R52*Расчеты!Q60) -> 1.1940523 | S60: =IF(S$9=Input!$H$9,1,Расчеты!S52*Расчеты!R60) -> 1.2298739 | ... AN60: =IF(AN$9=Input!$H$9,1,Расчеты!AN52*Расчеты!AM60) -> 0
C61: =Input!B25 -> Индекс роста заработной платы (RUB) | H61: х | L61: =IF(L$9=Input!$H$9,1,Расчеты!L53*Расчеты!K61) -> 1 | M61: =IF(M$9=Input!$H$9,1,Расчеты!M53*Расчеты!L61) -> 1.04 | N61: =IF(N$9=Input!$H$9,1,Расчеты!N53*Расчеты!M61) -> 1.0816 | O61: =IF(O$9=Input!$H$9,1,Расчеты!O53*Расчеты!N61) -> 1.124864 | P61: =IF(P$9=Input!$H$9,1,Расчеты!P53*Расчеты!O61) -> 1.1698586 | Q61: =IF(Q$9=Input!$H$9,1,Расчеты!Q53*Расчеты!P61) -> 1.2166529 | R61: =IF(R$9=Input!$H$9,1,Расчеты!R53*Расчеты!Q61) -> 1.265319 | S61: =IF(S$9=Input!$H$9,1,Расчеты!S53*Расчеты!R61) -> 1.3159318 | ... AN61: =IF(AN$9=Input!$H$9,1,Расчеты!AN53*Расчеты!AM61) -> 0
C62: =Input!B26 -> Индекс роста цен на естественные монополии (электроэнергия) | H62: х | L62: =IF(L$9=Input!$H$9,1,Расчеты!L54*Расчеты!K62) -> 1 | M62: =IF(M$9=Input!$H$9,1,Расчеты!M54*Расчеты!L62) -> 1.05 | N62: =IF(N$9=Input!$H$9,1,Расчеты!N54*Расчеты!M62) -> 1.1025 | O62: =IF(O$9=Input!$H$9,1,Расчеты!O54*Расчеты!N62) -> 1.157625 | P62: =IF(P$9=Input!$H$9,1,Расчеты!P54*Расчеты!O62) -> 1.2155063 | Q62: =IF(Q$9=Input!$H$9,1,Расчеты!Q54*Расчеты!P62) -> 1.2762816 | R62: =IF(R$9=Input!$H$9,1,Расчеты!R54*Расчеты!Q62) -> 1.3400956 | S62: =IF(S$9=Input!$H$9,1,Расчеты!S54*Расчеты!R62) -> 1.4071004 | ... AN62: =IF(AN$9=Input!$H$9,1,Расчеты!AN54*Расчеты!AM62) -> 0
C64: ПРОГНОЗ КАПИТАЛЬНЫХ И ПОДДЕРЖИВАЮЩИХ ВЛОЖЕНИЙ
C66: Финансирование капитальных вложений по годам (в реальных ценах, без НДС)
D67: Земля | H67: млн.руб. | L67: =IFERROR(Input!$H$43*Input!$H52*INDEX(Input!$K64:$Q64,MATCH(Расчеты!L$9,Input!$K$63:$Q$63,0)),0) -> 0 | M67: =IFERROR(Input!$H$43*Input!$H52*INDEX(Input!$K64:$Q64,MATCH(Расчеты!M$9,Input!$K$63:$Q$63,0)),0) -> 0 | N67: =IFERROR(Input!$H$43*Input!$H52*INDEX(Input!$K64:$Q64,MATCH(Расчеты!N$9,Input!$K$63:$Q$63,0)),0) -> 0 | O67: =IFERROR(Input!$H$43*Input!$H52*INDEX(Input!$K64:$Q64,MATCH(Расчеты!O$9,Input!$K$63:$Q$63,0)),0) -> 0 | P67: =IFERROR(Input!$H$43*Input!$H52*INDEX(Input!$K64:$Q64,MATCH(Расчеты!P$9,Input!$K$63:$Q$63,0)),0) -> 0 | Q67: =IFERROR(Input!$H$43*Input!$H52*INDEX(Input!$K64:$Q64,MATCH(Расчеты!Q$9,Input!$K$63:$Q$63,0)),0) -> 0 | R67: =IFERROR(Input!$H$43*Input!$H52*INDEX(Input!$K64:$Q64,MATCH(Расчеты!R$9,Input!$K$63:$Q$63,0)),0) -> 0 | S67: =IFERROR(Input!$H$43*Input!$H52*INDEX(Input!$K64:$Q64,MATCH(Расчеты!S$9,Input!$K$63:$Q$63,0)),0) -> 0 | ... AN67: =IFERROR(Input!$H$43*Input!$H52*INDEX(Input!$K64:$Q64,MATCH(Расчеты!AN$9,Input!$K$63:$Q$63,0)),0) -> 0
D68: Здания и сооружения | H68: млн.руб. | L68: =IFERROR(Input!$H$43*Input!$H53*INDEX(Input!$K65:$Q65,MATCH(Расчеты!L$9,Input!$K$63:$Q$63,0)),0) -> 0 | M68: =IFERROR(Input!$H$43*Input!$H53*INDEX(Input!$K65:$Q65,MATCH(Расчеты!M$9,Input!$K$63:$Q$63,0)),0) -> 21.5 | N68: =IFERROR(Input!$H$43*Input!$H53*INDEX(Input!$K65:$Q65,MATCH(Расчеты!N$9,Input!$K$63:$Q$63,0)),0) -> 21.5 | O68: =IFERROR(Input!$H$43*Input!$H53*INDEX(Input!$K65:$Q65,MATCH(Расчеты!O$9,Input!$K$63:$Q$63,0)),0) -> 0 | P68: =IFERROR(Input!$H$43*Input!$H53*INDEX(Input!$K65:$Q65,MATCH(Расчеты!P$9,Input!$K$63:$Q$63,0)),0) -> 0 | Q68: =IFERROR(Input!$H$43*Input!$H53*INDEX(Input!$K65:$Q65,MATCH(Расчеты!Q$9,Input!$K$63:$Q$63,0)),0) -> 0 | R68: =IFERROR(Input!$H$43*Input!$H53*INDEX(Input!$K65:$Q65,MATCH(Расчеты!R$9,Input!$K$63:$Q$63,0)),0) -> 0 | S68: =IFERROR(Input!$H$43*Input!$H53*INDEX(Input!$K65:$Q65,MATCH(Расчеты!S$9,Input!$K$63:$Q$63,0)),0) -> 0 | ... AN68: =IFERROR(Input!$H$43*Input!$H53*INDEX(Input!$K65:$Q65,MATCH(Расчеты!AN$9,Input!$K$63:$Q$63,0)),0) -> 0
D69: Оборудование | H69: млн.руб. | L69: =IFERROR(Input!$H$43*Input!$H54*INDEX(Input!$K66:$Q66,MATCH(Расчеты!L$9,Input!$K$63:$Q$63,0)),0) -> 0 | M69: =IFERROR(Input!$H$43*Input!$H54*INDEX(Input!$K66:$Q66,MATCH(Расчеты!M$9,Input!$K$63:$Q$63,0)),0) -> 75.25 | N69: =IFERROR(Input!$H$43*Input!$H54*INDEX(Input!$K66:$Q66,MATCH(Расчеты!N$9,Input!$K$63:$Q$63,0)),0) -> 75.25 | O69: =IFERROR(Input!$H$43*Input!$H54*INDEX(Input!$K66:$Q66,MATCH(Расчеты!O$9,Input!$K$63:$Q$63,0)),0) -> 0 | P69: =IFERROR(Input!$H$43*Input!$H54*INDEX(Input!$K66:$Q66,MATCH(Расчеты!P$9,Input!$K$63:$Q$63,0)),0) -> 0 | Q69: =IFERROR(Input!$H$43*Input!$H54*INDEX(Input!$K66:$Q66,MATCH(Расчеты!Q$9,Input!$K$63:$Q$63,0)),0) -> 0 | R69: =IFERROR(Input!$H$43*Input!$H54*INDEX(Input!$K66:$Q66,MATCH(Расчеты!R$9,Input!$K$63:$Q$63,0)),0) -> 0 | S69: =IFERROR(Input!$H$43*Input!$H54*INDEX(Input!$K66:$Q66,MATCH(Расчеты!S$9,Input!$K$63:$Q$63,0)),0) -> 0 | ... AN69: =IFERROR(Input!$H$43*Input!$H54*INDEX(Input!$K66:$Q66,MATCH(Расчеты!AN$9,Input!$K$63:$Q$63,0)),0) -> 0
D70: Транспорт | H70: млн.руб. | L70: =IFERROR(Input!$H$43*Input!$H55*INDEX(Input!$K67:$Q67,MATCH(Расчеты!L$9,Input!$K$63:$Q$63,0)),0) -> 0 | M70: =IFERROR(Input!$H$43*Input!$H55*INDEX(Input!$K67:$Q67,MATCH(Расчеты!M$9,Input!$K$63:$Q$63,0)),0) -> 10.75 | N70: =IFERROR(Input!$H$43*Input!$H55*INDEX(Input!$K67:$Q67,MATCH(Расчеты!N$9,Input!$K$63:$Q$63,0)),0) -> 10.75 | O70: =IFERROR(Input!$H$43*Input!$H55*INDEX(Input!$K67:$Q67,MATCH(Расчеты!O$9,Input!$K$63:$Q$63,0)),0) -> 0 | P70: =IFERROR(Input!$H$43*Input!$H55*INDEX(Input!$K67:$Q67,MATCH(Расчеты!P$9,Input!$K$63:$Q$63,0)),0) -> 0 | Q70: =IFERROR(Input!$H$43*Input!$H55*INDEX(Input!$K67:$Q67,MATCH(Расчеты!Q$9,Input!$K$63:$Q$63,0)),0) -> 0 | R70: =IFERROR(Input!$H$43*Input!$H55*INDEX(Input!$K67:$Q67,MATCH(Расчеты!R$9,Input!$K$63:$Q$63,0)),0) -> 0 | S70: =IFERROR(Input!$H$43*Input!$H55*INDEX(Input!$K67:$Q67,MATCH(Расчеты!S$9,Input!$K$63:$Q$63,0)),0) -> 0 | ... AN70: =IFERROR(Input!$H$43*Input!$H55*INDEX(Input!$K67:$Q67,MATCH(Расчеты!AN$9,Input!$K$63:$Q$63,0)),0) -> 0
C71: ИТОГО | H71: млн.руб. | L71: =SUM(L67:L70) -> 0 | M71: =SUM(M67:M70) -> 107.5 | N71: =SUM(N67:N70) -> 107.5 | O71: =SUM(O67:O70) -> 0 | P71: =SUM(P67:P70) -> 0 | Q71: =SUM(Q67:Q70) -> 0 | R71: =SUM(R67:R70) -> 0 | S71: =SUM(S67:S70) -> 0 | ... AN71: =SUM(AN67:AN70) -> 0
C73: Финансирование капитальных вложений по годам (в номинальных ценах, без НДС)
B74: =Input!A64 -> CPI, (RUB) | D74: Земля | H74: млн.руб. | I74: =SUM(L74:AN74) -> 0 | L74: =L67*INDEX(L$58:L$62,MATCH($B74,$C$58:$C$62,0)) -> 0 | M74: =M67*INDEX(M$58:M$62,MATCH($B74,$C$58:$C$62,0)) -> 0 | N74: =N67*INDEX(N$58:N$62,MATCH($B74,$C$58:$C$62,0)) -> 0 | O74: =O67*INDEX(O$58:O$62,MATCH($B74,$C$58:$C$62,0)) -> 0 | P74: =P67*INDEX(P$58:P$62,MATCH($B74,$C$58:$C$62,0)) -> 0 | Q74: =Q67*INDEX(Q$58:Q$62,MATCH($B74,$C$58:$C$62,0)) -> 0 | R74: =R67*INDEX(R$58:R$62,MATCH($B74,$C$58:$C$62,0)) -> 0 | S74: =S67*INDEX(S$58:S$62,MATCH($B74,$C$58:$C$62,0)) -> 0 | ... AN74: =AN67*INDEX(AN$58:AN$62,MATCH($B74,$C$58:$C$62,0)) -> 0
B75: =Input!A65 -> PPI, (RUB) | D75: Здания и сооружения | H75: млн.руб. | I75: =SUM(L75:AN75) -> 45.6144 | L75: =L68*INDEX(L$58:L$62,MATCH($B75,$C$58:$C$62,0)) -> 0 | M75: =M68*INDEX(M$58:M$62,MATCH($B75,$C$58:$C$62,0)) -> 22.36 | N75: =N68*INDEX(N$58:N$62,MATCH($B75,$C$58:$C$62,0)) -> 23.2544 | O75: =O68*INDEX(O$58:O$62,MATCH($B75,$C$58:$C$62,0)) -> 0 | P75: =P68*INDEX(P$58:P$62,MATCH($B75,$C$58:$C$62,0)) -> 0 | Q75: =Q68*INDEX(Q$58:Q$62,MATCH($B75,$C$58:$C$62,0)) -> 0 | R75: =R68*INDEX(R$58:R$62,MATCH($B75,$C$58:$C$62,0)) -> 0 | S75: =S68*INDEX(S$58:S$62,MATCH($B75,$C$58:$C$62,0)) -> 0 | ... AN75: =AN68*INDEX(AN$58:AN$62,MATCH($B75,$C$58:$C$62,0)) -> 0
B76: =Input!A66 -> PPI, (RUB) | D76: Оборудование | H76: млн.руб. | I76: =SUM(L76:AN76) -> 160.16331 | L76: =L69*(INDEX(L$58:L$62,MATCH($B76,$C$58:$C$62,0))*(1-Input!$H$45)+(L$60*Input!$H$45*(L$45/(INDEX($L$45:$AN$45,MATCH(Input!$H$15,Расчеты!$L$9:$AN$9,0)))))) -> 0 | M76: =M69*(INDEX(M$58:M$62,MATCH($B76,$C$58:$C$62,0))*(1-Input!$H$45)+(M$60*Input!$H$45*(M$45/(INDEX($L$45:$AN$45,MATCH(Input!$H$15,Расчеты!$L$9:$AN$9,0)))))) -> 78.428356 | N76: =N69*(INDEX(N$58:N$62,MATCH($B76,$C$58:$C$62,0))*(1-Input!$H$45)+(N$60*Input!$H$45*(N$45/(INDEX($L$45:$AN$45,MATCH(Input!$H$15,Расчеты!$L$9:$AN$9,0)))))) -> 81.734956 | O76: =O69*(INDEX(O$58:O$62,MATCH($B76,$C$58:$C$62,0))*(1-Input!$H$45)+(O$60*Input!$H$45*(O$45/(INDEX($L$45:$AN$45,MATCH(Input!$H$15,Расчеты!$L$9:$AN$9,0)))))) -> 0 | P76: =P69*(INDEX(P$58:P$62,MATCH($B76,$C$58:$C$62,0))*(1-Input!$H$45)+(P$60*Input!$H$45*(P$45/(INDEX($L$45:$AN$45,MATCH(Input!$H$15,Расчеты!$L$9:$AN$9,0)))))) -> 0 | Q76: =Q69*(INDEX(Q$58:Q$62,MATCH($B76,$C$58:$C$62,0))*(1-Input!$H$45)+(Q$60*Input!$H$45*(Q$45/(INDEX($L$45:$AN$45,MATCH(Input!$H$15,Расчеты!$L$9:$AN$9,0)))))) -> 0 | R76: =R69*(INDEX(R$58:R$62,MATCH($B76,$C$58:$C$62,0))*(1-Input!$H$45)+(R$60*Input!$H$45*(R$45/(INDEX($L$45:$AN$45,MATCH(Input!$H$15,Расчеты!$L$9:$AN$9,0)))))) -> 0 | S76: =S69*(INDEX(S$58:S$62,MATCH($B76,$C$58:$C$62,0))*(1-Input!$H$45)+(S$60*Input!$H$45*(S$45/(INDEX($L$45:$AN$45,MATCH(Input!$H$15,Расчеты!$L$9:$AN$9,0)))))) -> 0 | ... AN76: =AN69*(INDEX(AN$58:AN$62,MATCH($B76,$C$58:$C$62,0))*(1-Input!$H$45)+(AN$60*Input!$H$45*(AN$45/(INDEX($L$45:$AN$45,MATCH(Input!$H$15,Расчеты!$L$9:$AN$9,0)))))) -> 0
B77: =Input!A67 -> PPI, (RUB) | D77: Транспорт | H77: млн.руб. | I77: =SUM(L77:AN77) -> 22.880473 | L77: =L70*(INDEX(L$58:L$62,MATCH($B77,$C$58:$C$62,0))*(1-Input!$H$45)+(L$60*Input!$H$45*(L$45/(INDEX($L$45:$AN$45,MATCH(Input!$H$15,Расчеты!$L$9:$AN$9,0)))))) -> 0 | M77: =M70*(INDEX(M$58:M$62,MATCH($B77,$C$58:$C$62,0))*(1-Input!$H$45)+(M$60*Input!$H$45*(M$45/(INDEX($L$45:$AN$45,MATCH(Input!$H$15,Расчеты!$L$9:$AN$9,0)))))) -> 11.204051 | N77: =N70*(INDEX(N$58:N$62,MATCH($B77,$C$58:$C$62,0))*(1-Input!$H$45)+(N$60*Input!$H$45*(N$45/(INDEX($L$45:$AN$45,MATCH(Input!$H$15,Расчеты!$L$9:$AN$9,0)))))) -> 11.676422 | O77: =O70*(INDEX(O$58:O$62,MATCH($B77,$C$58:$C$62,0))*(1-Input!$H$45)+(O$60*Input!$H$45*(O$45/(INDEX($L$45:$AN$45,MATCH(Input!$H$15,Расчеты!$L$9:$AN$9,0)))))) -> 0 | P77: =P70*(INDEX(P$58:P$62,MATCH($B77,$C$58:$C$62,0))*(1-Input!$H$45)+(P$60*Input!$H$45*(P$45/(INDEX($L$45:$AN$45,MATCH(Input!$H$15,Расчеты!$L$9:$AN$9,0)))))) -> 0 | Q77: =Q70*(INDEX(Q$58:Q$62,MATCH($B77,$C$58:$C$62,0))*(1-Input!$H$45)+(Q$60*Input!$H$45*(Q$45/(INDEX($L$45:$AN$45,MATCH(Input!$H$15,Расчеты!$L$9:$AN$9,0)))))) -> 0 | R77: =R70*(INDEX(R$58:R$62,MATCH($B77,$C$58:$C$62,0))*(1-Input!$H$45)+(R$60*Input!$H$45*(R$45/(INDEX($L$45:$AN$45,MATCH(Input!$H$15,Расчеты!$L$9:$AN$9,0)))))) -> 0 | S77: =S70*(INDEX(S$58:S$62,MATCH($B77,$C$58:$C$62,0))*(1-Input!$H$45)+(S$60*Input!$H$45*(S$45/(INDEX($L$45:$AN$45,MATCH(Input!$H$15,Расчеты!$L$9:$AN$9,0)))))) -> 0 | ... AN77: =AN70*(INDEX(AN$58:AN$62,MATCH($B77,$C$58:$C$62,0))*(1-Input!$H$45)+(AN$60*Input!$H$45*(AN$45/(INDEX($L$45:$AN$45,MATCH(Input!$H$15,Расчеты!$L$9:$AN$9,0)))))) -> 0
C78: ИТОГО, без НДС | H78: млн.руб. | I78: =SUM(L78:AN78) -> 228.65818 | L78: =SUM(L74:L77) -> 0 | M78: =SUM(M74:M77) -> 111.99241 | N78: =SUM(N74:N77) -> 116.66578 | O78: =SUM(O74:O77) -> 0 | P78: =SUM(P74:P77) -> 0 | Q78: =SUM(Q74:Q77) -> 0 | R78: =SUM(R74:R77) -> 0 | S78: =SUM(S74:S77) -> 0 | ... AN78: =SUM(AN74:AN77) -> 0
C80: ИТОГО, капитальные вложения с НДС | H80: млн.руб. | I80: =SUM(L80:AN80) -> 274.38982 | L80: =((L78-L74)*(1+L34))+L74 -> 0 | M80: =((M78-M74)*(1+M34))+M74 -> 134.39089 | N80: =((N78-N74)*(1+N34))+N74 -> 139.99893 | O80: =((O78-O74)*(1+O34))+O74 -> 0 | P80: =((P78-P74)*(1+P34))+P74 -> 0 | Q80: =((Q78-Q74)*(1+Q34))+Q74 -> 0 | R80: =((R78-R74)*(1+R34))+R74 -> 0 | S80: =((S78-S74)*(1+S34))+S74 -> 0 | ... AN80: =((AN78-AN74)*(1+AN34))+AN74 -> 0
C82: Капитализированные проценты на стадии строительства | H82: млн.руб. | I82: =SUM(L82:AN82) -> 34.91573 | L82: =L740 -> 0 | M82: =M740 -> 27.415741 | N82: =N740 -> 7.4999885 | O82: =O740 -> 0 | P82: =P740 -> 0 | Q82: =Q740 -> 0 | R82: =R740 -> 0 | S82: =S740 -> 0 | ... AN82: =AN740 -> 0
C84: Капитальные вложения освоение по годам
D85: Земля | H85: млн.руб. | I85: =SUM(L85:AN85) -> 0 | L85: =IFERROR($I74*INDEX(Input!$K58:$Q58,MATCH(Расчеты!L$9,Input!$K$57:$Q$57,0)),0) -> 0 | M85: =IFERROR($I74*INDEX(Input!$K58:$Q58,MATCH(Расчеты!M$9,Input!$K$57:$Q$57,0)),0) -> 0 | N85: =IFERROR($I74*INDEX(Input!$K58:$Q58,MATCH(Расчеты!N$9,Input!$K$57:$Q$57,0)),0) -> 0 | O85: =IFERROR($I74*INDEX(Input!$K58:$Q58,MATCH(Расчеты!O$9,Input!$K$57:$Q$57,0)),0) -> 0 | P85: =IFERROR($I74*INDEX(Input!$K58:$Q58,MATCH(Расчеты!P$9,Input!$K$57:$Q$57,0)),0) -> 0 | Q85: =IFERROR($I74*INDEX(Input!$K58:$Q58,MATCH(Расчеты!Q$9,Input!$K$57:$Q$57,0)),0) -> 0 | R85: =IFERROR($I74*INDEX(Input!$K58:$Q58,MATCH(Расчеты!R$9,Input!$K$57:$Q$57,0)),0) -> 0 | S85: =IFERROR($I74*INDEX(Input!$K58:$Q58,MATCH(Расчеты!S$9,Input!$K$57:$Q$57,0)),0) -> 0 | ... AN85: =IFERROR($I74*INDEX(Input!$K58:$Q58,MATCH(Расчеты!AN$9,Input!$K$57:$Q$57,0)),0) -> 0
D86: Здания и сооружения | H86: млн.руб. | I86: =SUM(L86:AN86) -> 45.6144 | L86: =IFERROR($I75*INDEX(Input!$K59:$Q59,MATCH(Расчеты!L$9,Input!$K$57:$Q$57,0)),0) -> 0 | M86: =IFERROR($I75*INDEX(Input!$K59:$Q59,MATCH(Расчеты!M$9,Input!$K$57:$Q$57,0)),0) -> 22.8072 | N86: =IFERROR($I75*INDEX(Input!$K59:$Q59,MATCH(Расчеты!N$9,Input!$K$57:$Q$57,0)),0) -> 22.8072 | O86: =IFERROR($I75*INDEX(Input!$K59:$Q59,MATCH(Расчеты!O$9,Input!$K$57:$Q$57,0)),0) -> 0 | P86: =IFERROR($I75*INDEX(Input!$K59:$Q59,MATCH(Расчеты!P$9,Input!$K$57:$Q$57,0)),0) -> 0 | Q86: =IFERROR($I75*INDEX(Input!$K59:$Q59,MATCH(Расчеты!Q$9,Input!$K$57:$Q$57,0)),0) -> 0 | R86: =IFERROR($I75*INDEX(Input!$K59:$Q59,MATCH(Расчеты!R$9,Input!$K$57:$Q$57,0)),0) -> 0 | S86: =IFERROR($I75*INDEX(Input!$K59:$Q59,MATCH(Расчеты!S$9,Input!$K$57:$Q$57,0)),0) -> 0 | ... AN86: =IFERROR($I75*INDEX(Input!$K59:$Q59,MATCH(Расчеты!AN$9,Input!$K$57:$Q$57,0)),0) -> 0
D87: Оборудование | H87: млн.руб. | I87: =SUM(L87:AN87) -> 160.16331 | L87: =IFERROR($I76*INDEX(Input!$K60:$Q60,MATCH(Расчеты!L$9,Input!$K$57:$Q$57,0)),0) -> 0 | M87: =IFERROR($I76*INDEX(Input!$K60:$Q60,MATCH(Расчеты!M$9,Input!$K$57:$Q$57,0)),0) -> 120.12248 | N87: =IFERROR($I76*INDEX(Input!$K60:$Q60,MATCH(Расчеты!N$9,Input!$K$57:$Q$57,0)),0) -> 40.040828 | O87: =IFERROR($I76*INDEX(Input!$K60:$Q60,MATCH(Расчеты!O$9,Input!$K$57:$Q$57,0)),0) -> 0 | P87: =IFERROR($I76*INDEX(Input!$K60:$Q60,MATCH(Расчеты!P$9,Input!$K$57:$Q$57,0)),0) -> 0 | Q87: =IFERROR($I76*INDEX(Input!$K60:$Q60,MATCH(Расчеты!Q$9,Input!$K$57:$Q$57,0)),0) -> 0 | R87: =IFERROR($I76*INDEX(Input!$K60:$Q60,MATCH(Расчеты!R$9,Input!$K$57:$Q$57,0)),0) -> 0 | S87: =IFERROR($I76*INDEX(Input!$K60:$Q60,MATCH(Расчеты!S$9,Input!$K$57:$Q$57,0)),0) -> 0 | ... AN87: =IFERROR($I76*INDEX(Input!$K60:$Q60,MATCH(Расчеты!AN$9,Input!$K$57:$Q$57,0)),0) -> 0
D88: Транспорт | H88: млн.руб. | I88: =SUM(L88:AN88) -> 22.880473 | L88: =IFERROR($I77*INDEX(Input!$K61:$Q61,MATCH(Расчеты!L$9,Input!$K$57:$Q$57,0)),0) -> 0 | M88: =IFERROR($I77*INDEX(Input!$K61:$Q61,MATCH(Расчеты!M$9,Input!$K$57:$Q$57,0)),0) -> 5.7201183 | N88: =IFERROR($I77*INDEX(Input!$K61:$Q61,MATCH(Расчеты!N$9,Input!$K$57:$Q$57,0)),0) -> 17.160355 | O88: =IFERROR($I77*INDEX(Input!$K61:$Q61,MATCH(Расчеты!O$9,Input!$K$57:$Q$57,0)),0) -> 0 | P88: =IFERROR($I77*INDEX(Input!$K61:$Q61,MATCH(Расчеты!P$9,Input!$K$57:$Q$57,0)),0) -> 0 | Q88: =IFERROR($I77*INDEX(Input!$K61:$Q61,MATCH(Расчеты!Q$9,Input!$K$57:$Q$57,0)),0) -> 0 | R88: =IFERROR($I77*INDEX(Input!$K61:$Q61,MATCH(Расчеты!R$9,Input!$K$57:$Q$57,0)),0) -> 0 | S88: =IFERROR($I77*INDEX(Input!$K61:$Q61,MATCH(Расчеты!S$9,Input!$K$57:$Q$57,0)),0) -> 0 | ... AN88: =IFERROR($I77*INDEX(Input!$K61:$Q61,MATCH(Расчеты!AN$9,Input!$K$57:$Q$57,0)),0) -> 0
C89: ИТОГО | H89: млн.руб. | I89: =SUM(L89:AN89) -> 228.65818 | L89: =SUM(L85:L88) -> 0 | M89: =SUM(M85:M88) -> 148.6498 | N89: =SUM(N85:N88) -> 80.008383 | O89: =SUM(O85:O88) -> 0 | P89: =SUM(P85:P88) -> 0 | Q89: =SUM(Q85:Q88) -> 0 | R89: =SUM(R85:R88) -> 0 | S89: =SUM(S85:S88) -> 0 | ... AN89: =SUM(AN85:AN88) -> 0
C91: Авансы выданные/задолженность поставщикам и подрядчикам | H91: млн.руб. | K91: 0 | L91: =K91+L89-L78 -> 0 | M91: =L91+M89-M78 -> 36.657395 | N91: =M91+N89-N78 -> 0 | O91: =N91+O89-O78 -> 0 | P91: =O91+P89-P78 -> 0 | Q91: =P91+Q89-Q78 -> 0 | R91: =Q91+R89-R78 -> 0 | S91: =R91+S89-S78 -> 0 | ... AN91: =AM91+AN89-AN78 -> 0
C93: Распределение капитализированных процентов
D94: Земля | H94: млн.руб. | I94: =SUM(L94:AN94) -> 0 | L94: =IFERROR(L$82*L67/L$71,0) -> 0 | M94: =IFERROR(M$82*M67/M$71,0) -> 0 | N94: =IFERROR(N$82*N67/N$71,0) -> 0 | O94: =IFERROR(O$82*O67/O$71,0) -> 0 | P94: =IFERROR(P$82*P67/P$71,0) -> 0 | Q94: =IFERROR(Q$82*Q67/Q$71,0) -> 0 | R94: =IFERROR(R$82*R67/R$71,0) -> 0 | S94: =IFERROR(S$82*S67/S$71,0) -> 0 | ... AN94: =IFERROR(AN$82*AN67/AN$71,0) -> 0
D95: Здания и сооружения | H95: млн.руб. | I95: =SUM(L95:AN95) -> 6.9831459 | L95: =IFERROR(L$82*L68/L$71,0) -> 0 | M95: =IFERROR(M$82*M68/M$71,0) -> 5.4831482 | N95: =IFERROR(N$82*N68/N$71,0) -> 1.4999977 | O95: =IFERROR(O$82*O68/O$71,0) -> 0 | P95: =IFERROR(P$82*P68/P$71,0) -> 0 | Q95: =IFERROR(Q$82*Q68/Q$71,0) -> 0 | R95: =IFERROR(R$82*R68/R$71,0) -> 0 | S95: =IFERROR(S$82*S68/S$71,0) -> 0 | ... AN95: =IFERROR(AN$82*AN68/AN$71,0) -> 0
D96: Оборудование | H96: млн.руб. | I96: =SUM(L96:AN96) -> 24.441011 | L96: =IFERROR(L$82*L69/L$71,0) -> 0 | M96: =IFERROR(M$82*M69/M$71,0) -> 19.191019 | N96: =IFERROR(N$82*N69/N$71,0) -> 5.2499919 | O96: =IFERROR(O$82*O69/O$71,0) -> 0 | P96: =IFERROR(P$82*P69/P$71,0) -> 0 | Q96: =IFERROR(Q$82*Q69/Q$71,0) -> 0 | R96: =IFERROR(R$82*R69/R$71,0) -> 0 | S96: =IFERROR(S$82*S69/S$71,0) -> 0 | ... AN96: =IFERROR(AN$82*AN69/AN$71,0) -> 0
D97: Транспорт | H97: млн.руб. | I97: =SUM(L97:AN97) -> 3.491573 | L97: =IFERROR(L$82*L70/L$71,0) -> 0 | M97: =IFERROR(M$82*M70/M$71,0) -> 2.7415741 | N97: =IFERROR(N$82*N70/N$71,0) -> 0.74999885 | O97: =IFERROR(O$82*O70/O$71,0) -> 0 | P97: =IFERROR(P$82*P70/P$71,0) -> 0 | Q97: =IFERROR(Q$82*Q70/Q$71,0) -> 0 | R97: =IFERROR(R$82*R70/R$71,0) -> 0 | S97: =IFERROR(S$82*S70/S$71,0) -> 0 | ... AN97: =IFERROR(AN$82*AN70/AN$71,0) -> 0
C98: ИТОГО | H98: млн.руб. | I98: =SUM(L98:AN98) -> 34.91573 | L98: =SUM(L94:L97) -> 0 | M98: =SUM(M94:M97) -> 27.415741 | N98: =SUM(N94:N97) -> 7.4999885 | O98: =SUM(O94:O97) -> 0 | P98: =SUM(P94:P97) -> 0 | Q98: =SUM(Q94:Q97) -> 0 | R98: =SUM(R94:R97) -> 0 | S98: =SUM(S94:S97) -> 0 | ... AN98: =SUM(AN94:AN97) -> 0
C100: Капитальные вложения освоение по годам (с учетом капитализации процентов)
D101: Земля | H101: млн.руб. | I101: =SUM(L101:AN101) -> 0 | L101: =L85+L94 -> 0 | M101: =M85+M94 -> 0 | N101: =N85+N94 -> 0 | O101: =O85+O94 -> 0 | P101: =P85+P94 -> 0 | Q101: =Q85+Q94 -> 0 | R101: =R85+R94 -> 0 | S101: =S85+S94 -> 0 | ... AN101: =AN85+AN94 -> 0
D102: Здания и сооружения | H102: млн.руб. | I102: =SUM(L102:AN102) -> 52.597546 | L102: =L86+L95 -> 0 | M102: =M86+M95 -> 28.290348 | N102: =N86+N95 -> 24.307198 | O102: =O86+O95 -> 0 | P102: =P86+P95 -> 0 | Q102: =Q86+Q95 -> 0 | R102: =R86+R95 -> 0 | S102: =S86+S95 -> 0 | ... AN102: =AN86+AN95 -> 0
D103: Оборудование | H103: млн.руб. | I103: =SUM(L103:AN103) -> 184.60432 | L103: =L87+L96 -> 0 | M103: =M87+M96 -> 139.3135 | N103: =N87+N96 -> 45.29082 | O103: =O87+O96 -> 0 | P103: =P87+P96 -> 0 | Q103: =Q87+Q96 -> 0 | R103: =R87+R96 -> 0 | S103: =S87+S96 -> 0 | ... AN103: =AN87+AN96 -> 0
D104: Транспорт | H104: млн.руб. | I104: =SUM(L104:AN104) -> 26.372046 | L104: =L88+L97 -> 0 | M104: =M88+M97 -> 8.4616924 | N104: =N88+N97 -> 17.910354 | O104: =O88+O97 -> 0 | P104: =P88+P97 -> 0 | Q104: =Q88+Q97 -> 0 | R104: =R88+R97 -> 0 | S104: =S88+S97 -> 0 | ... AN104: =AN88+AN97 -> 0
C105: ИТОГО | H105: млн.руб. | I105: =SUM(L105:AN105) -> 263.57391 | L105: =SUM(L101:L104) -> 0 | M105: =SUM(M101:M104) -> 176.06554 | N105: =SUM(N101:N104) -> 87.508371 | O105: =SUM(O101:O104) -> 0 | P105: =SUM(P101:P104) -> 0 | Q105: =SUM(Q101:Q104) -> 0 | R105: =SUM(R101:R104) -> 0 | S105: =SUM(S101:S104) -> 0 | ... AN105: =SUM(AN101:AN104) -> 0
C107: Ремонтатная программа зданий и сооружений
D108: Количество лет эксплуатации | H108: лет | L108: =Input!K94 -> 1 | M108: =Input!L94 -> 2 | N108: =Input!M94 -> 3 | O108: =Input!N94 -> 4 | P108: =Input!O94 -> 5 | Q108: =Input!P94 -> 6 | R108: =Input!Q94 -> 7 | S108: =Input!R94 -> 8 | ... AC108: =Input!AB94 -> 18
D109: Вид ремонта | H109: выбор | L109: =Input!K95 -> ТР | M109: =Input!L95 -> ТР | N109: =Input!M95 -> ТР | O109: =Input!N95 -> ТР | P109: =Input!O95 -> СР | Q109: =Input!P95 -> КР | R109: =Input!Q95 -> ТР | S109: =Input!R95 -> ТР | ... AC109: =Input!AB95 -> ТР
B111: =Input!A97 -> CPI, (RUB) | C111: Расходы на ремонт зданий и сооружений
D112: ТР | H112: млн руб. | I112: =Input!H98 -> 1.2 | L112: =$I112*INDEX(L$58:L$62,MATCH($B$111,$C$58:$C$62,0))*L27 -> 0 | M112: =$I112*INDEX(M$58:M$62,MATCH($B$111,$C$58:$C$62,0))*M27 -> 0 | N112: =$I112*INDEX(N$58:N$62,MATCH($B$111,$C$58:$C$62,0))*N27 -> 1.29792 | O112: =$I112*INDEX(O$58:O$62,MATCH($B$111,$C$58:$C$62,0))*O27 -> 1.3498368 | P112: =$I112*INDEX(P$58:P$62,MATCH($B$111,$C$58:$C$62,0))*P27 -> 1.4038303 | Q112: =$I112*INDEX(Q$58:Q$62,MATCH($B$111,$C$58:$C$62,0))*Q27 -> 1.4599835 | R112: =$I112*INDEX(R$58:R$62,MATCH($B$111,$C$58:$C$62,0))*R27 -> 0 | S112: =$I112*INDEX(S$58:S$62,MATCH($B$111,$C$58:$C$62,0))*S27 -> 0 | ... AN112: =$I112*INDEX(AN$58:AN$62,MATCH($B$111,$C$58:$C$62,0))*AN27 -> 0
D113: СР | H113: млн руб. | I113: =Input!H99 -> 2.5 | L113: =$I113*INDEX(L$58:L$62,MATCH($B$111,$C$58:$C$62,0))*L28 -> 0 | M113: =$I113*INDEX(M$58:M$62,MATCH($B$111,$C$58:$C$62,0))*M28 -> 0 | N113: =$I113*INDEX(N$58:N$62,MATCH($B$111,$C$58:$C$62,0))*N28 -> 0 | O113: =$I113*INDEX(O$58:O$62,MATCH($B$111,$C$58:$C$62,0))*O28 -> 0 | P113: =$I113*INDEX(P$58:P$62,MATCH($B$111,$C$58:$C$62,0))*P28 -> 0 | Q113: =$I113*INDEX(Q$58:Q$62,MATCH($B$111,$C$58:$C$62,0))*Q28 -> 0 | R113: =$I113*INDEX(R$58:R$62,MATCH($B$111,$C$58:$C$62,0))*R28 -> 3.1632975 | S113: =$I113*INDEX(S$58:S$62,MATCH($B$111,$C$58:$C$62,0))*S28 -> 0 | ... AN113: =$I113*INDEX(AN$58:AN$62,MATCH($B$111,$C$58:$C$62,0))*AN28 -> 0
D114: КР | H114: млн руб. | I114: =Input!H100 -> 3.4 | L114: =$I114*INDEX(L$58:L$62,MATCH($B$111,$C$58:$C$62,0))*L29 -> 0 | M114: =$I114*INDEX(M$58:M$62,MATCH($B$111,$C$58:$C$62,0))*M29 -> 0 | N114: =$I114*INDEX(N$58:N$62,MATCH($B$111,$C$58:$C$62,0))*N29 -> 0 | O114: =$I114*INDEX(O$58:O$62,MATCH($B$111,$C$58:$C$62,0))*O29 -> 0 | P114: =$I114*INDEX(P$58:P$62,MATCH($B$111,$C$58:$C$62,0))*P29 -> 0 | Q114: =$I114*INDEX(Q$58:Q$62,MATCH($B$111,$C$58:$C$62,0))*Q29 -> 0 | R114: =$I114*INDEX(R$58:R$62,MATCH($B$111,$C$58:$C$62,0))*R29 -> 0 | S114: =$I114*INDEX(S$58:S$62,MATCH($B$111,$C$58:$C$62,0))*S29 -> 4.474168 | ... AN114: =$I114*INDEX(AN$58:AN$62,MATCH($B$111,$C$58:$C$62,0))*AN29 -> 0
C115: ИТОГО | H115: млн руб. | I115: =SUM(L115:AN115) -> 36.253259 | L115: =SUM(L112:L114) -> 0 | M115: =SUM(M112:M114) -> 0 | N115: =SUM(N112:N114) -> 1.29792 | O115: =SUM(O112:O114) -> 1.3498368 | P115: =SUM(P112:P114) -> 1.4038303 | Q115: =SUM(Q112:Q114) -> 1.4599835 | R115: =SUM(R112:R114) -> 3.1632975 | S115: =SUM(S112:S114) -> 4.474168 | ... AN115: =SUM(AN112:AN114) -> 0
C117: Ремонтная программа оборудования
D118: Кумулятивный объем производства | H118: т | L118: =Input!K75 -> 75000 | M118: =Input!L75 -> 150000 | N118: =Input!M75 -> 225000 | O118: =Input!N75 -> 300000 | P118: =Input!O75 -> 350000 | Q118: =Input!P75 -> 425000 | R118: =Input!Q75 -> 500000 | S118: =Input!R75 -> 575000 | ... AC118: =Input!AB75 -> 1300000
D119: Вид ремонта | H119: выбор | L119: =Input!K76 -> ТР | M119: =Input!L76 -> ТР | N119: =Input!M76 -> ТР | O119: =Input!N76 -> ТР | P119: =Input!O76 -> СР | Q119: =Input!P76 -> ТР | R119: =Input!Q76 -> ТР | S119: =Input!R76 -> ТР | ... AC119: =Input!AB76 -> ТР
B121: =Input!A78 -> PPI, (RUB) | C121: Расходы на ремонт оборудования
D122: ТР | H122: млн руб. | I122: =Input!H79 -> 8.5 | L122: =$I122*INDEX(L$58:L$62,MATCH($B$121,$C$58:$C$62,0))*L21 -> 0 | M122: =$I122*INDEX(M$58:M$62,MATCH($B$121,$C$58:$C$62,0))*M21 -> 0 | N122: =$I122*INDEX(N$58:N$62,MATCH($B$121,$C$58:$C$62,0))*N21 -> 0 | O122: =$I122*INDEX(O$58:O$62,MATCH($B$121,$C$58:$C$62,0))*O21 -> 9.561344 | P122: =$I122*INDEX(P$58:P$62,MATCH($B$121,$C$58:$C$62,0))*P21 -> 9.9437978 | Q122: =$I122*INDEX(Q$58:Q$62,MATCH($B$121,$C$58:$C$62,0))*Q21 -> 10.34155 | R122: =$I122*INDEX(R$58:R$62,MATCH($B$121,$C$58:$C$62,0))*R21 -> 0 | S122: =$I122*INDEX(S$58:S$62,MATCH($B$121,$C$58:$C$62,0))*S21 -> 11.18542 | ... AN122: =$I122*INDEX(AN$58:AN$62,MATCH($B$121,$C$58:$C$62,0))*AN21 -> 0
D123: СР | H123: млн руб. | I123: =Input!H80 -> 15.3 | L123: =$I123*INDEX(L$58:L$62,MATCH($B$121,$C$58:$C$62,0))*L22 -> 0 | M123: =$I123*INDEX(M$58:M$62,MATCH($B$121,$C$58:$C$62,0))*M22 -> 0 | N123: =$I123*INDEX(N$58:N$62,MATCH($B$121,$C$58:$C$62,0))*N22 -> 0 | O123: =$I123*INDEX(O$58:O$62,MATCH($B$121,$C$58:$C$62,0))*O22 -> 0 | P123: =$I123*INDEX(P$58:P$62,MATCH($B$121,$C$58:$C$62,0))*P22 -> 0 | Q123: =$I123*INDEX(Q$58:Q$62,MATCH($B$121,$C$58:$C$62,0))*Q22 -> 0 | R123: =$I123*INDEX(R$58:R$62,MATCH($B$121,$C$58:$C$62,0))*R22 -> 19.359381 | S123: =$I123*INDEX(S$58:S$62,MATCH($B$121,$C$58:$C$62,0))*S22 -> 0 | ... AN123: =$I123*INDEX(AN$58:AN$62,MATCH($B$121,$C$58:$C$62,0))*AN22 -> 0
D124: КР | H124: млн руб. | I124: =Input!H81 -> 20.4 | L124: =$I124*INDEX(L$58:L$62,MATCH($B$121,$C$58:$C$62,0))*L23 -> 0 | M124: =$I124*INDEX(M$58:M$62,MATCH($B$121,$C$58:$C$62,0))*M23 -> 0 | N124: =$I124*INDEX(N$58:N$62,MATCH($B$121,$C$58:$C$62,0))*N23 -> 0 | O124: =$I124*INDEX(O$58:O$62,MATCH($B$121,$C$58:$C$62,0))*O23 -> 0 | P124: =$I124*INDEX(P$58:P$62,MATCH($B$121,$C$58:$C$62,0))*P23 -> 0 | Q124: =$I124*INDEX(Q$58:Q$62,MATCH($B$121,$C$58:$C$62,0))*Q23 -> 0 | R124: =$I124*INDEX(R$58:R$62,MATCH($B$121,$C$58:$C$62,0))*R23 -> 0 | S124: =$I124*INDEX(S$58:S$62,MATCH($B$121,$C$58:$C$62,0))*S23 -> 0 | ... AN124: =$I124*INDEX(AN$58:AN$62,MATCH($B$121,$C$58:$C$62,0))*AN23 -> 0
C125: ИТОГО | H125: млн руб. | I125: =SUM(L125:AN125) -> 214.57466 | L125: =SUM(L122:L124) -> 0 | M125: =SUM(M122:M124) -> 0 | N125: =SUM(N122:N124) -> 0 | O125: =SUM(O122:O124) -> 9.561344 | P125: =SUM(P122:P124) -> 9.9437978 | Q125: =SUM(Q122:Q124) -> 10.34155 | R125: =SUM(R122:R124) -> 19.359381 | S125: =SUM(S122:S124) -> 11.18542 | ... AN125: =SUM(AN122:AN124) -> 0
...

Sheet PL_BS_CF
A1: =Title!$C$16 -> Строительство производства сухих строительных смесей
A2: =Title!$C$15 -> Финансово-экономическая модель | L2: {=Input!L2:L4} -> 45292 | M2: {=Input!M2:M4} -> 45658 | N2: {=Input!N2:N4} -> 46023 | O2: {=Input!O2:O4} -> 46388 | P2: {=Input!P2:P4} -> 46753 | Q2: {=Input!Q2:Q4} -> 47119 | R2: {=Input!R2:R4} -> 47484 | S2: {=Input!S2:S4} -> 47849 | ... AN2: {=Input!AN2:AN4}
A3: Прогноз 3-х форм финансовой отчетности | L3: 45657 | M3: 46022 | N3: 46387 | O3: 46752 | P3: 47118 | Q3: 47483 | R3: 47848 | S3: 48213 | T3: 48579 | U3: 48944 | V3: 49309 | W3: 49674 | X3: 50040 | Y3: 50405 | Z3: 50770 | AA3: 51135 | AB3: 51501 | AC3: 51866
L4: Факт | M4: Прогноз | N4: Прогноз | O4: Прогноз | P4: Прогноз | Q4: Прогноз | R4: Прогноз | S4: Прогноз | T4: Прогноз | U4: Прогноз | V4: Прогноз | W4: Прогноз | X4: Прогноз | Y4: Прогноз | Z4: Прогноз | AA4: Прогноз | AB4: Прогноз | AC4: Прогноз
G5: Ед. измерения | H5: Значение/База | K5: Сумма
B7: PL
B9: Выручка | G9: млн. руб. | K9: =SUM(L9:AN9) -> 16563.793 | L9: =Расчеты!L444 -> 0 | M9: =Расчеты!M444 -> 0 | N9: =Расчеты!N444 -> 684.26283 | O9: =Расчеты!O444 -> 853.96001 | P9: =Расчеты!P444 -> 890.55161 | Q9: =Расчеты!Q444 -> 923.64315 | R9: =Расчеты!R444 -> 960.58888 | S9: =Расчеты!S444 -> 999.01243 | ... AN9: =Расчеты!AN444 -> 0
B11: Себестоимость | G11: млн. руб. | K11: =SUM(L11:AN11) -> 12524.967 | L11: =Расчеты!L603 -> 0 | M11: =Расчеты!M603 -> 0 | N11: =Расчеты!N603 -> 558.15789 | O11: =Расчеты!O603 -> 696.60167 | P11: =Расчеты!P603 -> 726.47228 | Q11: =Расчеты!Q603 -> 753.48961 | R11: =Расчеты!R603 -> 783.65307 | S11: =Расчеты!S603 -> 815.02425 | ... AN11: =Расчеты!AN603 -> 0
B13: Маржинальная прибыль | G13: млн. руб. | K13: =SUM(L13:AN13) -> 4038.826 | L13: =L9-L11 -> 0 | M13: =M9-M11 -> 0 | N13: =N9-N11 -> 126.10494 | O13: =O9-O11 -> 157.35834 | P13: =P9-P11 -> 164.07933 | Q13: =Q9-Q11 -> 170.15353 | R13: =R9-R11 -> 176.93581 | S13: =S9-S11 -> 183.98818 | ... AN13: =AN9-AN11 -> 0
B14: % рентабельность по маржинальной прибыли | L14: =IFERROR(L13/L9,0) -> 0 | M14: =IFERROR(M13/M9,0) -> 0 | N14: =IFERROR(N13/N9,0) -> 0.18429313 | O14: =IFERROR(O13/O9,0) -> 0.18426898 | P14: =IFERROR(P13/P9,0) -> 0.1842446 | Q14: =IFERROR(Q13/Q9,0) -> 0.18421999 | R14: =IFERROR(R13/R9,0) -> 0.18419514 | S14: =IFERROR(S13/S9,0) -> 0.18417006 | ... AN14: =IFERROR(AN13/AN9,0) -> 0
B16: Общепроизводственные и административные расходы | G16: млн. руб. | K16: =SUM(L16:AN16) -> 1658.7136 | L16: =Расчеты!L619+Расчеты!L627 -> 0 | M16: =Расчеты!M619+Расчеты!M627 -> 0 | N16: =Расчеты!N619+Расчеты!N627 -> 68.534347 | O16: =Расчеты!O619+Расчеты!O627 -> 85.536929 | P16: =Расчеты!P619+Расчеты!P627 -> 88.964773 | Q16: =Расчеты!Q619+Расчеты!Q627 -> 92.530049 | R16: =Расчеты!R619+Расчеты!R627 -> 96.238271 | S16: =Расчеты!S619+Расчеты!S627 -> 100.09517 | ... AN16: =Расчеты!AN619+Расчеты!AN627 -> 0
B18: Расходы на текущий ремонт | G18: млн. руб. | K18: =SUM(L18:AN18) -> 247.42017 | L18: =Расчеты!L632 -> 0 | M18: =Расчеты!M632 -> 0 | N18: =Расчеты!N632 -> 1.29792 | O18: =Расчеты!O632 -> 13.723341 | P18: =Расчеты!P632 -> 14.272274 | Q18: =Расчеты!Q632 -> 14.843165 | R18: =Расчеты!R632 -> 25.685976 | S18: =Расчеты!S632 -> 14.47525 | ... AN18: =Расчеты!AN632 -> 0
B20: Налоги (кроме налога на прибыль) | G20: млн. руб. | K20: =SUM(L20:AN20) -> 9.4096749 | L20: =Расчеты!L807+Расчеты!L817+Расчеты!L825 -> 0 | M20: =Расчеты!M807+Расчеты!M817+Расчеты!M825 -> 0 | N20: =Расчеты!N807+Расчеты!N817+Расчеты!N825 -> 2.1840576 | O20: =Расчеты!O807+Расчеты!O817+Расчеты!O825 -> 2.0071786 | P20: =Расчеты!P807+Расчеты!P817+Расчеты!P825 -> 1.5528347 | Q20: =Расчеты!Q807+Расчеты!Q817+Расчеты!Q825 -> 1.0984908 | R20: =Расчеты!R807+Расчеты!R817+Расчеты!R825 -> 0.64414687 | S20: =Расчеты!S807+Расчеты!S817+Расчеты!S825 -> 0.37747952 | ... AN20: =Расчеты!AN807+Расчеты!AN817+Расчеты!AN825 -> 0
B22: EBITDА | G22: млн. руб. | K22: =SUM(L22:AN22) -> 2123.2826 | L22: =L13-L16-L18-L20 -> 0 | M22: =M13-M16-M18-M20 -> 0 | N22: =N13-N16-N18-N20 -> 54.088612 | O22: =O13-O16-O18-O20 -> 56.090894 | P22: =P13-P16-P18-P20 -> 59.289448 | Q22: =Q13-Q16-Q18-Q20 -> 61.681829 | R22: =R13-R16-R18-R20 -> 54.367413 | S22: =S13-S16-S18-S20 -> 69.040275 | ... AN22: =AN13-AN16-AN18-AN20 -> 0
B23: % рентабельность по EBITDA | L23: =IFERROR(L22/L9,0) -> 0 | M23: =IFERROR(M22/M9,0) -> 0 | N23: =IFERROR(N22/N9,0) -> 0.079046544 | O23: =IFERROR(O22/O9,0) -> 0.065683279 | P23: =IFERROR(P22/P9,0) -> 0.066576094 | Q23: =IFERROR(Q22/Q9,0) -> 0.066781017 | R23: =IFERROR(R22/R9,0) -> 0.056598004 | S23: =IFERROR(S22/S9,0) -> 0.069108525 | ... AN23: =IFERROR(AN22/AN9,0) -> 0
B25: Амортизация | G25: млн. руб. | K25: =SUM(L25:AN25) -> 354.82757 | L25: =Расчеты!L152 -> 0 | M25: =Расчеты!M152 -> 0 | N25: =Расчеты!N152 -> 36.617665 | O25: =Расчеты!O152 -> 43.941198 | P25: =Расчеты!P152 -> 43.941198 | Q25: =Расчеты!Q152 -> 43.941198 | R25: =Расчеты!R152 -> 43.941198 | S25: =Расчеты!S152 -> 14.292353 | ... AN25: =Расчеты!AN152 -> 0
B27: EBIT | G27: млн. руб. | K27: =SUM(L27:AN27) -> 1768.455 | L27: =L22-L25 -> 0 | M27: =M22-M25 -> 0 | N27: =N22-N25 -> 17.470947 | O27: =O22-O25 -> 12.149696 | P27: =P22-P25 -> 15.34825 | Q27: =Q22-Q25 -> 17.740631 | R27: =R22-R25 -> 10.426215 | S27: =S22-S25 -> 54.747923 | ... AN27: =AN22-AN25 -> 0
B28: % рентабельность по EBIT | L28: =IFERROR(L27/L9,0) -> 0 | M28: =IFERROR(M27/M9,0) -> 0 | N28: =IFERROR(N27/N9,0) -> 0.02553251 | O28: =IFERROR(O27/O9,0) -> 0.014227476 | P28: =IFERROR(P27/P9,0) -> 0.017234543 | Q28: =IFERROR(Q27/Q9,0) -> 0.019207235 | R28: =IFERROR(R27/R9,0) -> 0.010853983 | S28: =IFERROR(S27/S9,0) -> 0.054802043 | ... AN28: =IFERROR(AN27/AN9,0) -> 0
B30: Процентные расходы | G30: млн. руб. | K30: =SUM(L30:AN30) -> 168.80782 | L30: =Расчеты!L741 -> 0 | M30: =Расчеты!M741 -> 0 | N30: =Расчеты!N741 -> 37.499942 | O30: =Расчеты!O741 -> 32.400404 | P30: =Расчеты!P741 -> 26.849149 | Q30: =Расчеты!Q741 -> 20.260063 | R30: =Расчеты!R741 -> 15.866096 | S30: =Расчеты!S741 -> 12.972875 | ... AN30: =Расчеты!AN741 -> 0
B32: EBT | G32: млн. руб. | K32: =SUM(L32:AN32) -> 1599.6472 | L32: =L27-L30 -> 0 | M32: =M27-M30 -> 0 | N32: =N27-N30 -> -20.028995 | O32: =O27-O30 -> -20.250708 | P32: =P27-P30 -> -11.500899 | Q32: =Q27-Q30 -> -2.5194321 | R32: =R27-R30 -> -5.4398812 | S32: =S27-S30 -> 41.775048 | ... AN32: =AN27-AN30 -> 0
B33: % рентабельность по EBT | L33: =IFERROR(L32/L9,0) -> 0 | M33: =IFERROR(M32/M9,0) -> 0 | N33: =IFERROR(N32/N9,0) -> -0.029270909 | O33: =IFERROR(O32/O9,0) -> -0.023713884 | P33: =IFERROR(P32/P9,0) -> -0.012914354 | Q33: =IFERROR(Q32/Q9,0) -> -0.0027277116 | R33: =IFERROR(R32/R9,0) -> -0.0056630691 | S33: =IFERROR(S32/S9,0) -> 0.041816344 | ... AN33: =IFERROR(AN32/AN9,0) -> 0
B35: Налог на прибыль | G35: млн. руб. | K35: =SUM(L35:AN35) -> 414.84678 | L35: =Расчеты!L843 -> 0 | M35: =Расчеты!M843 -> 0 | N35: =Расчеты!N843 -> 0 | O35: =Расчеты!O843 -> 0 | P35: =Расчеты!P843 -> 0 | Q35: =Расчеты!Q843 -> 0 | R35: =Расчеты!R843 -> 0 | S35: =Расчеты!S843 -> 10.443762 | ... AN35: =Расчеты!AN843 -> 0
B37: Чистая прибыль | K37: =SUM(L37:AN37) -> 1184.8004 | L37: =L32-L35 -> 0 | M37: =M32-M35 -> 0 | N37: =N32-N35 -> -20.028995 | O37: =O32-O35 -> -20.250708 | P37: =P32-P35 -> -11.500899 | Q37: =Q32-Q35 -> -2.5194321 | R37: =R32-R35 -> -5.4398812 | S37: =S32-S35 -> 31.331286 | ... AN37: =AN32-AN35 -> 0
B38: % рентабельность по чистой прибыли | G38: % | L38: =IFERROR(L37/L$9,0) -> 0 | M38: =IFERROR(M37/M$9,0) -> 0 | N38: =IFERROR(N37/N$9,0) -> -0.029270909 | O38: =IFERROR(O37/O$9,0) -> -0.023713884 | P38: =IFERROR(P37/P$9,0) -> -0.012914354 | Q38: =IFERROR(Q37/Q$9,0) -> -0.0027277116 | R38: =IFERROR(R37/R$9,0) -> -0.0056630691 | S38: =IFERROR(S37/S$9,0) -> 0.031362258 | ... AN38: =IFERROR(AN37/AN$9,0) -> 0
B40: Долг/EBITDA | G40: x | L40: =IFERROR((L63+L66)/L22,0) -> 0 | M40: =IFERROR((M63+M66)/M22,0) -> 0 | N40: =IFERROR((N63+N66)/N22,0) -> 3.6304516 | O40: =IFERROR((O63+O66)/O22,0) -> 3.0882074 | P40: =IFERROR((P63+P66)/P22,0) -> 2.5312184 | Q40: =IFERROR((Q63+Q66)/Q22,0) -> 2.0577984 | R40: =IFERROR((R63+R66)/R22,0) -> 1.9089192 | S40: =IFERROR((S63+S66)/S22,0) -> 1.1679737 | ... AN40: =IFERROR((AN63+AN66)/AN22,0) -> 0
B42: BS
B44: ВНЕОБОРОТНЫЕ АКТИВЫ | G44: млн. руб. | L44: =SUM(L45:L46) -> 0 | M44: =SUM(M45:M46) -> 176.06554 | N44: =SUM(N45:N46) -> 226.95625 | O44: =SUM(O45:O46) -> 183.01505 | P44: =SUM(P45:P46) -> 139.07385 | Q44: =SUM(Q45:Q46) -> 95.132656 | R44: =SUM(R45:R46) -> 51.191458 | S44: =SUM(S45:S46) -> 41.373273 | ... AN44: =SUM(AN45:AN46) -> 7.1054274e-14
C45: Основные средства | G45: млн. руб. | L45: =Расчеты!L154 -> 0 | M45: =Расчеты!M154 -> 0 | N45: =Расчеты!N154 -> 226.95625 | O45: =Расчеты!O154 -> 183.01505 | P45: =Расчеты!P154 -> 139.07385 | Q45: =Расчеты!Q154 -> 95.132656 | R45: =Расчеты!R154 -> 51.191458 | S45: =Расчеты!S154 -> 41.373273 | ... AN45: =Расчеты!AN154 -> 0
C46: Незавершенные капитальные вложения | G46: млн. руб. | L46: =Расчеты!L148 -> 0 | M46: =Расчеты!M148 -> 176.06554 | N46: =Расчеты!N148 -> 0 | O46: =Расчеты!O148 -> 0 | P46: =Расчеты!P148 -> 0 | Q46: =Расчеты!Q148 -> 0 | R46: =Расчеты!R148 -> 0 | S46: =Расчеты!S148 -> 1.7763568e-14 | ... AN46: =Расчеты!AN148 -> 7.1054274e-14
B48: ОБОРОТНЫЕ АКТИВЫ | L48: =SUM(L49:L54) -> 0 | M48: =SUM(M49:M54) -> 22.398481 | N48: =SUM(N49:N54) -> 138.87799 | O48: =SUM(O49:O54) -> 149.44107 | P48: =SUM(P49:P54) -> 161.56214 | Q48: =SUM(Q49:Q54) -> 182.85258 | R48: =SUM(R49:R54) -> 201.59629 | S48: =SUM(S49:S54) -> 227.1989 | ... AN48: =SUM(AN49:AN54) -> 1327.029
C49: Запасы | G49: млн. руб. | L49: =Расчеты!L923 -> 0 | M49: =Расчеты!M923 -> 0 | N49: =Расчеты!N923 -> 18.293906 | O49: =Расчеты!O923 -> 19.025662 | P49: =Расчеты!P923 -> 19.786689 | Q49: =Расчеты!Q923 -> 20.578156 | R49: =Расчеты!R923 -> 21.401283 | S49: =Расчеты!S923 -> 22.257334 | ... AN49: =Расчеты!AN923 -> 0
C50: Дебиторская задолженость | G50: млн. руб. | L50: =Расчеты!L922+Расчеты!L924 -> 0 | M50: =Расчеты!M922+Расчеты!M924 -> 5.5229132 | N50: =Расчеты!N922+Расчеты!N924 -> 67.488937 | O50: =Расчеты!O922+Расчеты!O924 -> 70.188494 | P50: =Расчеты!P922+Расчеты!P924 -> 72.996034 | Q50: =Расчеты!Q922+Расчеты!Q924 -> 75.915875 | R50: =Расчеты!R922+Расчеты!R924 -> 78.95251 | S50: =Расчеты!S922+Расчеты!S924 -> 82.110611 | ... AN50: =Расчеты!AN922+Расчеты!AN924 -> 0
C51: НДС на балансе | G51: млн. руб. | L51: =Расчеты!L894 -> 0 | M51: =Расчеты!M894 -> 0 | N51: =Расчеты!N894 -> 0 | O51: =Расчеты!O894 -> 0 | P51: =Расчеты!P894 -> 0 | Q51: =Расчеты!Q894 -> 0 | R51: =Расчеты!R894 -> 0 | S51: =Расчеты!S894 -> 0 | ... AN51: =Расчеты!AN894 -> 0
C52: Денежные средства | G52: млн. руб. | L52: =L96 -> 0 | M52: =M96 -> 16.875568 | N52: =N96 -> 53.095143 | O52: =O96 -> 60.226915 | P52: =P96 -> 68.779413 | Q52: =Q96 -> 85.946064 | R52: =R96 -> 100.78259 | S52: =S96 -> 122.83095 | ... AN52: =AN96 -> 1327.029
C53: Авансы выданные поставщикам за капитальные вложения | G53: млн. руб. | L53: =IF(Расчеты!L91<0,-Расчеты!L91,0) -> 0 | M53: =IF(Расчеты!M91<0,-Расчеты!M91,0) -> 0 | N53: =IF(Расчеты!N91<0,-Расчеты!N91,0) -> 0 | O53: =IF(Расчеты!O91<0,-Расчеты!O91,0) -> 0 | P53: =IF(Расчеты!P91<0,-Расчеты!P91,0) -> 0 | Q53: =IF(Расчеты!Q91<0,-Расчеты!Q91,0) -> 0 | R53: =IF(Расчеты!R91<0,-Расчеты!R91,0) -> 0 | S53: =IF(Расчеты!S91<0,-Расчеты!S91,0) -> 0 | ... AN53: =IF(Расчеты!AN91<0,-Расчеты!AN91,0) -> 0
C54: Отложенные налоговые активы | G54: млн. руб. | L54: =IF(Расчеты!L876>0,Расчеты!L876,0) -> 0 | M54: =IF(Расчеты!M876>0,Расчеты!M876,0) -> 0 | N54: =IF(Расчеты!N876>0,Расчеты!N876,0) -> 0 | O54: =IF(Расчеты!O876>0,Расчеты!O876,0) -> 0 | P54: =IF(Расчеты!P876>0,Расчеты!P876,0) -> 0 | Q54: =IF(Расчеты!Q876>0,Расчеты!Q876,0) -> 0.41248202 | R54: =IF(Расчеты!R876>0,Расчеты!R876,0) -> 0.4599079 | S54: =IF(Расчеты!S876>0,Расчеты!S876,0) -> 0 | ... AN54: =IF(Расчеты!AN876>0,Расчеты!AN876,0) -> 0
B56: ИТОГО АКТИВ | G56: млн. руб. | L56: =L44+L48 -> 0 | M56: =M44+M48 -> 198.46402 | N56: =N44+N48 -> 365.83424 | O56: =O44+O48 -> 332.45612 | P56: =P44+P48 -> 300.63599 | Q56: =Q44+Q48 -> 277.98523 | R56: =R44+R48 -> 252.78775 | S56: =S44+S48 -> 268.57217 | ... AN56: =AN44+AN48 -> 1327.029
B58: КАПИТАЛ И РЕЗЕРВЫ | G58: млн. руб. | L58: =L59+L60 -> 0 | M58: =M59+M60 -> 54.293919 | N58: =N59+N60 -> 107.26464 | O58: =O59+O60 -> 87.013933 | P58: =P59+P60 -> 75.513034 | Q58: =Q59+Q60 -> 72.993602 | R58: =R59+R60 -> 67.553721 | S58: =S59+S60 -> 98.885007 | ... AN58: =AN59+AN60 -> 1312.094
C59: Уставной капитал | G59: млн. руб. | L59: =K59+L89 -> 0 | M59: =L59+M89 -> 54.293919 | N59: =M59+N89 -> 127.29364 | O59: =N59+O89 -> 127.29364 | P59: =O59+P89 -> 127.29364 | Q59: =P59+Q89 -> 127.29364 | R59: =Q59+R89 -> 127.29364 | S59: =R59+S89 -> 127.29364 | ... AN59: =AM59+AN89 -> 127.29364
C60: Нераспределенная прибыль | G60: млн. руб. | L60: =L37+K60 -> 0 | M60: =M37+L60 -> 0 | N60: =N37+M60 -> -20.028995 | O60: =O37+N60 -> -40.279703 | P60: =P37+O60 -> -51.780602 | Q60: =Q37+P60 -> -54.300034 | R60: =R37+Q60 -> -59.739915 | S60: =S37+R60 -> -28.40863 | ... AN60: =AN37+AM60 -> 1184.8004
B62: ДОЛГОСРОЧНЫЕ ОБЯЗАТЕЛЬСТВА | G62: млн. руб. | L62: =L63 -> 0 | M62: =M63 -> 84.366939 | N62: =N63 -> 173.22031 | O62: =O63 -> 150.07454 | P62: =P63 -> 126.92877 | Q62: =Q63 -> 103.783 | R62: =R63 -> 80.637229 | S62: =S63 -> 57.491458 | ... AN62: =AN63 -> 0
C63: Долгосрочные кредиты и займы | G63: млн. руб. | L63: =Расчеты!L745 -> 0 | M63: =Расчеты!M745 -> 84.366939 | N63: =Расчеты!N745 -> 173.22031 | O63: =Расчеты!O745 -> 150.07454 | P63: =Расчеты!P745 -> 126.92877 | Q63: =Расчеты!Q745 -> 103.783 | R63: =Расчеты!R745 -> 80.637229 | S63: =Расчеты!S745 -> 57.491458 | ... AN63: =Расчеты!AN745 -> 0
B65: КРАТКОСРОЧНЫЕ ОБЯЗАТЕЛЬСТВА | G65: млн. руб. | L65: =SUM(L66:L69) -> 0 | M65: =SUM(M66:M69) -> 59.803167 | N65: =SUM(N66:N69) -> 85.34928 | O65: =SUM(O66:O69) -> 95.367647 | P65: =SUM(P66:P69) -> 98.194183 | Q65: =SUM(Q66:Q69) -> 101.20863 | R65: =SUM(R66:R69) -> 104.5968 | S65: =SUM(S66:S69) -> 112.19571 | ... AN65: =SUM(AN66:AN69) -> 14.934979
C66: Краткосрочные кредиты и займы | G66: млн. руб. | L66: =Расчеты!L744 -> 0 | M66: =Расчеты!M744 -> 23.145771 | N66: =Расчеты!N744 -> 23.145771 | O66: =Расчеты!O744 -> 23.145771 | P66: =Расчеты!P744 -> 23.145771 | Q66: =Расчеты!Q744 -> 23.145771 | R66: =Расчеты!R744 -> 23.145771 | S66: =Расчеты!S744 -> 23.145771 | ... AN66: =Расчеты!AN744 -> 0
C67: Кредиторская задолженость | G67: млн. руб. | L67: =Расчеты!L925+Расчеты!L927 -> 0 | M67: =Расчеты!M925+Расчеты!M927 -> 0 | N67: =Расчеты!N925+Расчеты!N927 -> 62.203508 | O67: =Расчеты!O925+Расчеты!O927 -> 72.221875 | P67: =Расчеты!P925+Расчеты!P927 -> 75.048412 | Q67: =Расчеты!Q925+Расчеты!Q927 -> 78.062859 | R67: =Расчеты!R925+Расчеты!R927 -> 81.45103 | S67: =Расчеты!S925+Расчеты!S927 -> 84.506185 | ... AN67: =Расчеты!AN925+Расчеты!AN927 -> 0
C68: Кредиторская задолженность перед поставщиками по капитальным вложениям | G68: млн. руб. | L68: =IF(Расчеты!L91>0,Расчеты!L91,0) -> 0 | M68: =IF(Расчеты!M91>0,Расчеты!M91,0) -> 36.657395 | N68: =IF(Расчеты!N91>0,Расчеты!N91,0) -> 0 | O68: =IF(Расчеты!O91>0,Расчеты!O91,0) -> 0 | P68: =IF(Расчеты!P91>0,Расчеты!P91,0) -> 0 | Q68: =IF(Расчеты!Q91>0,Расчеты!Q91,0) -> 0 | R68: =IF(Расчеты!R91>0,Расчеты!R91,0) -> 0 | S68: =IF(Расчеты!S91>0,Расчеты!S91,0) -> 0 | ... AN68: =IF(Расчеты!AN91>0,Расчеты!AN91,0) -> 0
C69: Отложенные налоговые обязательства | G69: млн. руб. | L69: =IF(Расчеты!L876<0,-Расчеты!L876,0) -> 0 | M69: =IF(Расчеты!M876<0,-Расчеты!M876,0) -> 0 | N69: =IF(Расчеты!N876<0,-Расчеты!N876,0) -> 0 | O69: =IF(Расчеты!O876<0,-Расчеты!O876,0) -> 0 | P69: =IF(Расчеты!P876<0,-Расчеты!P876,0) -> 0 | Q69: =IF(Расчеты!Q876<0,-Расчеты!Q876,0) -> 0 | R69: =IF(Расчеты!R876<0,-Расчеты!R876,0) -> 0 | S69: =IF(Расчеты!S876<0,-Расчеты!S876,0) -> 4.5437497 | ... AN69: =IF(Расчеты!AN876<0,-Расчеты!AN876,0) -> 14.934979
B71: ИТОГО ПАССИВ | G71: млн. руб. | L71: =L58+L62+L65 -> 0 | M71: =M58+M62+M65 -> 198.46402 | N71: =N58+N62+N65 -> 365.83424 | O71: =O58+O62+O65 -> 332.45612 | P71: =P58+P62+P65 -> 300.63599 | Q71: =Q58+Q62+Q65 -> 277.98523 | R71: =R58+R62+R65 -> 252.78775 | S71: =S58+S62+S65 -> 268.57217 | ... AN71: =AN58+AN62+AN65 -> 1327.029
B73: Проверка баланса | G73: х | L73: =L56-L71 -> 0 | M73: =M56-M71 -> 0 | N73: =N56-N71 -> 0 | O73: =O56-O71 -> 0 | P73: =P56-P71 -> 0 | Q73: =Q56-Q71 -> 0 | R73: =R56-R71 -> 0 | S73: =S56-S71 -> 0 | ... AN73: =AN56-AN71 -> 0
B75: CF
B77: Чистая прибыль | G77: млн. руб. | L77: =L37 -> 0 | M77: =M37 -> 0 | N77: =N37 -> -20.028995 | O77: =O37 -> -20.250708 | P77: =P37 -> -11.500899 | Q77: =Q37 -> -2.5194321 | R77: =R37 -> -5.4398812 | S77: =S37 -> 31.331286 | ... AN77: =AN37 -> 0
B78: (+) Налог на прибыль (по бухгалтерскому учету) | G78: млн. руб. | L78: =L35 -> 0 | M78: =M35 -> 0 | N78: =N35 -> 0 | O78: =O35 -> 0 | P78: =P35 -> 0 | Q78: =Q35 -> 0 | R78: =R35 -> 0 | S78: =S35 -> 10.443762 | ... AN78: =AN35 -> 0
B79: (-) Налог на прибыль (по налоговому учету) | G79: млн. руб. | L79: =-Расчеты!L874 -> 0 | M79: =-Расчеты!M874 -> 0 | N79: =-Расчеты!N874 -> 0 | O79: =-Расчеты!O874 -> 0 | P79: =-Расчеты!P874 -> 0 | Q79: =-Расчеты!Q874 -> -0.41248202 | R79: =-Расчеты!R874 -> -0.047425884 | S79: =-Расчеты!S874 -> -5.4401043 | ... AN79: =-Расчеты!AN874 -> 0
B80: (+) Амортизация | G80: млн. руб. | L80: =L25 -> 0 | M80: =M25 -> 0 | N80: =N25 -> 36.617665 | O80: =O25 -> 43.941198 | P80: =P25 -> 43.941198 | Q80: =Q25 -> 43.941198 | R80: =R25 -> 43.941198 | S80: =S25 -> 14.292353 | ... AN80: =AN25 -> 0
B81: (+/-) Изменение оборотного капитала | G81: млн. руб. | L81: =-Расчеты!L930 -> 0 | M81: =-Расчеты!M930 -> -5.5229132 | N81: =-Расчеты!N930 -> -18.056421 | O81: =-Расчеты!O930 -> 6.5870532 | P81: =-Расчеты!P930 -> -0.74202967 | Q81: =-Расчеты!Q930 -> -0.69686128 | R81: =-Расчеты!R930 -> -0.47159072 | S81: =-Расчеты!S930 -> -0.95899647 | ... AN81: =-Расчеты!AN930 -> 0
B82: (+) Процентые расходы | G82: млн. руб. | L82: =L30 -> 0 | M82: =M30 -> 0 | N82: =N30 -> 37.499942 | O82: =O30 -> 32.400404 | P82: =P30 -> 26.849149 | Q82: =Q30 -> 20.260063 | R82: =R30 -> 15.866096 | S82: =S30 -> 12.972875 | ... AN82: =AN30 -> 0
B83: (+/-) Чистый ДП по НДС | G83: млн. руб. | L83: =Расчеты!L899 -> 0 | M83: =Расчеты!M899 -> 0 | N83: =Расчеты!N899 -> 0 | O83: =Расчеты!O899 -> 0 | P83: =Расчеты!P899 -> 0 | Q83: =Расчеты!Q899 -> 0 | R83: =Расчеты!R899 -> 0 | S83: =Расчеты!S899 -> 0 | ... AN83: =Расчеты!AN899 -> 0
B84: Денежный поток от операционной деятельности | G84: млн. руб. | L84: =SUM(L77:L83) -> 0 | M84: =SUM(M77:M83) -> -5.5229132 | N84: =SUM(N77:N83) -> 36.032191 | O84: =SUM(O77:O83) -> 62.677947 | P84: =SUM(P77:P83) -> 58.547418 | Q84: =SUM(Q77:Q83) -> 60.572486 | R84: =SUM(R77:R83) -> 53.848397 | S84: =SUM(S77:S83) -> 62.641175 | ... AN84: =SUM(AN77:AN83) -> 0
B86: (-) Капитальные затраты | G86: млн. руб. | L86: =-(Расчеты!L78+Расчеты!L114+Расчеты!L124+Расчеты!L136) -> 0 | M86: =-(Расчеты!M78+Расчеты!M114+Расчеты!M124+Расчеты!M136) -> -111.99241 | N86: =-(Расчеты!N78+Расчеты!N114+Расчеты!N124+Расчеты!N136) -> -116.66578 | O86: =-(Расчеты!O78+Расчеты!O114+Расчеты!O124+Расчеты!O136) -> 0 | P86: =-(Расчеты!P78+Расчеты!P114+Расчеты!P124+Расчеты!P136) -> 0 | Q86: =-(Расчеты!Q78+Расчеты!Q114+Расчеты!Q124+Расчеты!Q136) -> 0 | R86: =-(Расчеты!R78+Расчеты!R114+Расчеты!R124+Расчеты!R136) -> 0 | S86: =-(Расчеты!S78+Расчеты!S114+Расчеты!S124+Расчеты!S136) -> -4.474168 | ... AN86: =-(Расчеты!AN78+Расчеты!AN114+Расчеты!AN124+Расчеты!AN136) -> 0
B87: Денежный поток от инвестиционной деятельности | G87: млн. руб. | L87: =L86 -> 0 | M87: =M86 -> -111.99241 | N87: =N86 -> -116.66578 | O87: =O86 -> 0 | P87: =P86 -> 0 | Q87: =Q86 -> 0 | R87: =R86 -> 0 | S87: =S86 -> -4.474168 | ... AN87: =AN86 -> 0
B89: (+) Взнос в УК | G89: млн. руб. | L89: =Расчеты!L791 -> 0 | M89: =Расчеты!M791 -> 54.293919 | N89: =Расчеты!N791 -> 72.999717 | O89: =Расчеты!O791 -> 0 | P89: =Расчеты!P791 -> 0 | Q89: =Расчеты!Q791 -> 0 | R89: =Расчеты!R791 -> 0 | S89: =Расчеты!S791 -> 0 | ... AN89: =Расчеты!AN791 -> 0
B90: (+) Привлечение кредита | G90: млн. руб. | L90: =Расчеты!L751 -> 0 | M90: =Расчеты!M751 -> 107.51271 | N90: =Расчеты!N751 -> 111.99915 | O90: =Расчеты!O751 -> 0 | P90: =Расчеты!P751 -> 0 | Q90: =Расчеты!Q751 -> 0 | R90: =Расчеты!R751 -> 0 | S90: =Расчеты!S751 -> 0 | ... AN90: =Расчеты!AN751 -> 0
B91: (-) Возврат кредита | G91: млн. руб. | L91: =-Расчеты!L739 -> 0 | M91: =-Расчеты!M739 -> 0 | N91: =-Расчеты!N739 -> -23.145771 | O91: =-Расчеты!O739 -> -23.145771 | P91: =-Расчеты!P739 -> -23.145771 | Q91: =-Расчеты!Q739 -> -23.145771 | R91: =-Расчеты!R739 -> -23.145771 | S91: =-Расчеты!S739 -> -23.145771 | ... AN91: =-Расчеты!AN739 -> 0
B92: (-) Процентные расходы к уплате | G92: млн. руб. | L92: =-Расчеты!L738 -> 0 | M92: =-Расчеты!M738 -> -27.415741 | N92: =-Расчеты!N738 -> -44.999931 | O92: =-Расчеты!O738 -> -32.400404 | P92: =-Расчеты!P738 -> -26.849149 | Q92: =-Расчеты!Q738 -> -20.260063 | R92: =-Расчеты!R738 -> -15.866096 | S92: =-Расчеты!S738 -> -12.972875 | ... AN92: =-Расчеты!AN738 -> 0
B93: Денежный поток от финансовой деятельности | G93: млн. руб. | L93: =SUM(L89:L92) -> 0 | M93: =SUM(M89:M92) -> 134.39089 | N93: =SUM(N89:N92) -> 116.85316 | O93: =SUM(O89:O92) -> -55.546176 | P93: =SUM(P89:P92) -> -49.99492 | Q93: =SUM(Q89:Q92) -> -43.405835 | R93: =SUM(R89:R92) -> -39.011868 | S93: =SUM(S89:S92) -> -36.118646 | ... AN93: =SUM(AN89:AN92) -> 0
B95: Чистый денежный поток за период | G95: млн. руб. | L95: =L84+L87+L93 -> 0 | M95: =M84+M87+M93 -> 16.875568 | N95: =N84+N87+N93 -> 36.219575 | O95: =O84+O87+O93 -> 7.1317714 | P95: =P84+P87+P93 -> 8.5524981 | Q95: =Q84+Q87+Q93 -> 17.166651 | R95: =R84+R87+R93 -> 14.836529 | S95: =S84+S87+S93 -> 22.04836 | ... AN95: =AN84+AN87+AN93 -> 0
B96: Денежный средства на конец периода | G96: млн. руб. | L96: =K96+L95 -> 0 | M96: =L96+M95 -> 16.875568 | N96: =M96+N95 -> 53.095143 | O96: =N96+O95 -> 60.226915 | P96: =O96+P95 -> 68.779413 | Q96: =P96+Q95 -> 85.946064 | R96: =Q96+R95 -> 100.78259 | S96: =R96+S95 -> 122.83095 | ... AN96: =AM96+AN95 -> 1327.029
B98: Проверка | G98: х | H98: =MIN(0,L96:AN96) -> 0
B100: КОНЕЦ ЛИСТА

Sheet Тех.лист
C2: Индексация | E2: Ремонты | G2: Тип платежа
C3: Без индексации | E3: ТР | G3: Аннуитетный платеж
C4: CPI, (RUB) | E4: СР | G4: Дифференцированный платеж
C5: PPI, (RUB) | E5: КР
C6: PPI, (USD)
C7: Индекс роста заработной платы (RUB)
C8: Индекс роста цен на естественные монополии (электроэнергия)
O127: ПЕРЕФОРМУЛИРОВАТЬ

Sheet Лист2
